Workbook
Name Slicer_Grouped_age: #N/A
Name Slicer_Sector: #N/A

Sheet Uncleaned_DS_jobs
A1: index | B1: Job Title | C1: Salary Estimate | D1: Job Description | E1: Rating | F1: Company Name | G1: Location | H1: Headquarters | I1: Size | J1: Founded | K1: Type of ownership | L1: Industry | M1: Sector | N1: Revenue | O1: Competitors
A2: 0 | B2: Sr Data Scientist | C2: $137K-$171K (Glassdoor est.) | D2: Description The Senior Data Scientist is responsible for defining, building, and improving statistical models to improve business processes and outcomes in one or more healthcare domains such as Clinical, Enrollment, Claims, and Finance. As part of the broader analytics team, Data Scientist will gather and analyze data to solve and address complex business problems and evaluate scenarios to make predictions on future outcomes and work with the business to communicate and support decision-making. This position requires strong analytical skills and experience in analytic methods including multivariate regressions, hierarchical linear models, regression trees, clustering methods and other complex statistical techniques. Duties & Responsibilities: вЂў Develops advanced statistical models to predict, quantify or forecast various operational and performance metrics in multiple healthcare domains вЂў Investigates, recommends, and initiates acquisition of new data resources from internal and external sources вЂў Works with multiple teams to support data collection, integration, and retention requirements based on business needs вЂў Identifies critical and emerging technologies that will support and extend quantitative analytic capabilities вЂў Collaborates with business subject matter experts to select relevant sources of information вЂў Develops expertise with multiple machine learning algorithms and data science techniques, such as exploratory data analysis and predictive modeling, graph theory, recommender systems, text analytics and validation вЂў Develops expertise with Healthfirst datasets, data repositories, and data movement processes вЂў Assists on projects/requests and may lead specific tasks within the project scope вЂў Prepares and manipulates data for use in development of statistical models вЂў Other duties as assigned Minimum Qualifications: -Bachelor's Degree Preferred Qualifications: - MasterвЂ™s degree in Computer Science or Statistics Familiarity with major cloud platforms such as AWS and Azure Healthcare Industry Experience Minimum Qualifications: -Bachelor's Degree Preferred Qualifications: - MasterвЂ™s degree in Computer Science or Statistics Familiarity with major cloud platforms such as AWS and Azure Healthcare Industry Experience WE ARE AN EQUAL OPPORTUNITY EMPLOYER. Applicants and employees are considered for positions and are evaluated without regard to mental or physical disability, race, color, religion, gender, national origin, age, genetic information, military or veteran status, sexual orientation, marital status or any other protected Federal, State/Province or Local status unrelated to the performance of the work involved. If you have a disability under the Americans with Disability Act or a similar law, and want a reasonable accommodation to assist with your job search or application for employment, please contact us by sending an email to careers@Healthfirst.org or calling 212-519-1798 . In your email please include a description of the accommodation you are requesting and a description of the position for which you are applying. Only reasonable accommodation requests related to applying for a position within Healthfirst Management Services will be reviewed at the e-mail address and phone number supplied. Thank you for considering a career with Healthfirst Management Services. EEO Law Poster and Supplement ]]> | E2: 3.1 | F2: Healthfirst 3.1 | G2: New York, NY | H2: New York, NY | I2: 1001 to 5000 employees | J2: 1993 | K2: Nonprofit Organization | L2: Insurance Carriers | M2: Insurance | N2: Unknown / Non-Applicable | O2: EmblemHealth, UnitedHealth Group, Aetna
A3: 1 | B3: Data Scientist | C3: $137K-$171K (Glassdoor est.) | D3: Secure our Nation, Ignite your Future Join the top Information Technology and Analytic professionals in the industry to make invaluable contributions to our national security on a daily basis. In this innovative, self-contained, Big Data environment, the ManTech team is responsible for everything from infrastructure, to application development, to data science, to advanced analytics and beyond. The team is diverse, the questions are thought-provoking, and the opportunities for growth and advancement are numerous The successful candidate will possess a diverse range of data-focused skills and experience, both technical and analytical. They will have a strong desire and capability for problem solving, data analysis and troubleshooting, analytical thinking, and experimentation. Duties, Tasks & Responsibilities Working with large, complex, and disparate data sets Designing and implementing innovative ways to analyze and exploit the Sponsors data holdings Researching and reporting on a wide variety of Sponsor inquiries Raising proactive inquiries to the Sponsor based on observations and proposed data analysis/exploitation Solving difficult, non-routine problems by applying advanced analytical methodologies, and improving analytic methodologies Developing custom searches Communicating and coordinating with internal and external partners as needed Required Experience, Skills, & Technologies Thorough knowledge of appropriate analytic tools and methodologies in one or more of the following: Applied mathematics (e.g. probability and statistics, formal modeling, computational social sciences) Computer programming (e.g. programming languages, math/statistics packages, computer science, machine learning, scientific computing) Ability to code or script in one or more general programming language Experience with and theoretical understanding of algorithms for classification, regression, clustering, and anomaly detection Knowledge of relational databases, including SQL and large-scale distributed systems (e.g. Hadoop) Expertise with statistical data analysis (e.g. linear models, multivariate analysis, stochastic models, sampling methods) Demonstrated effectiveness in collecting information and accurately representing/visualizing it to non-technical third parties TS/SCI with Polygraph Bachelor of Science or equivalent and 12-15 years related experience, but will consider all levels of experience. Desired Experience, Skills & Technologies Previous investigative experience using a combination of technical and analytic skills #LI-DU1 ManTech International Corporation, as well as its subsidiaries proactively fulfills its role as an equal opportunity employer. We do not discriminate against any employee or applicant for employment because of race, color, sex, religion, age, sexual orientation, gender identity and expression, national origin, marital status, physical or mental disability, status as a Disabled Veteran, Recently Separated Veteran, Active Duty Wartime or Campaign Badge Veteran, Armed Forces Services Medal, or any other characteristic protected by law. If you require a reasonable accommodation to apply for a position with ManTech through its online applicant system, please contact ManTech's Corporate EEO Department at (703) 218-6000. ManTech is an affirmative action/equal opportunity employer - minorities, females, disabled and protected veterans are urged to apply. ManTech's utilization of any external recruitment or job placement agency is predicated upon its full compliance with our equal opportunity/affirmative action policies. ManTech does not accept resumes from unsolicited recruiting firms. We pay no fees for unsolicited services. If you are a qualified individual with a disability or a disabled veteran, you have the right to request an accommodation if you are unable or limited in your ability to use or access http://www.mantech.com/careers/Pages/careers.aspx as a result of your disability. To request an accommodation please click careers@mantech.com and provide your name and contact information. | E3: 4.2 | F3: ManTech 4.2 | G3: Chantilly, VA | H3: Herndon, VA | I3: 5001 to 10000 employees | J3: 1968 | K3: Company - Public | L3: Research & Development | M3: Business Services | N3: $1 to $2 billion (USD) | O3: -1
A4: 2 | B4: Data Scientist | C4: $137K-$171K (Glassdoor est.) | D4: Overview Analysis Group is one of the largest international economics consulting firms, with more than 1,000 professionals across 14 offices in North America, Europe, and Asia. Since 1981, we have provided expertise in economics, finance, health care analytics, and strategy to top law firms, Fortune Global 500 companies, and government agencies worldwide. Our internal experts, together with our network of affiliated experts from academia, industry, and government, offer our clients exceptional breadth and depth of expertise. We are currently seeking a Data Scientist to join our team. The ideal candidate should be passionate about working on cutting edge research and analytical services for Fortune 500 companies, global pharma/biotech firms and leaders in industries such as finance, energy and life sciences. The Data Scientist will be a contributing member to client engagements and have the opportunity to work with our network of world-class experts and thought leaders. Job Functions and Responsibilities The candidate Data Scientist will help develop, maintain and teach new tools and methodologies related to data science and high performance computing. This position will also help Analysis Group in maintaining our leadership position in terms of advancing methodology and data analytics. The Data Scientist will be responsible for staying abreast of new developments in technology relating to data science, to share more broadly with Analysis Group. Key responsibilities for this position will include: Working with project teams to address data science/computing challenges Identifying opportunities for technology to enhance service offerings Acting as a resource and participating in client engagements and research as part of the project team Maintaining up-to-date knowledge of computing tools, providing technical training and helping to grow the in-house knowledge base, specifically in a Linux environment Presenting research at selected conferences Examples of activities for the Data Scientist will include: Developing data engineering and machine learning production systems for full stack data science projects Using natural language processing methodologies to work with EMR data, social media data and other unstructured data Optimizing procedures for managing and accessing large databases (e.g., insurance claims, electronic health records, financial transactions) Creating interactive analytics portals and data visualizations (e.g., using R/Shiny, Python/Flask, D3) Building and maintaining high performance computing (HPC) tools on grid and cloud computing environments Developing and reviewing software and packages in R, Python and other Object Oriented Languages Establishing optimized procedures for repetitive or computationally intensive tasks (C, C++, Cuda-C) Qualifications Strong credentials and experience in database management and data visualization Significant experience working within a Linux environment required Background in Statistics/Econometrics or Biostatistics Ideally PhD in Computer Science, Mathematics, Statistics, Economics or other relevant scientific degree with relevant experience. Other candidates with at least one year of experience in the field may also be considered Excellent written and verbal communication skills Project experience with R and/or Python Familiar with online/cloud computing/storage (e.g., AWS) Demonstrated experience working on project teams and collaborating with others SCIENTIFIQUE DES DONNГ‰ES *LвЂ™utilisation du genre masculin sert uniquement Г allГ©ger le texte et est utilisГ© ici en tant que genre neutre Survol Groupe dвЂ™analyse ltГ©e est lвЂ™une des plus grandes firmes de services-conseils en Г©conomie, comptant plus de 950 professionnels rГ©partis dans 14 bureaux en AmГ©rique du Nord, en Europe et en Asie. Depuis 1981, nous offrons notre expertise en matiГЁre de stratГ©gie, dвЂ™Г©conomie, de finance et dвЂ™analyse dans le domaine des soins de santГ© aux grands cabinets dвЂ™avocats, aux sociГ©tГ©s Fortune Global 500 et aux agences gouvernementales du monde entier. Nos professionnels en poste conjuguГ©s Г notre rГ©seau de spГ©cialistes affiliГ©s issus dвЂ™universitГ©s, dвЂ™industries spГ©cifiques et dвЂ™organismes gouvernementaux procurent Г notre clientГЁle un savoir-faire dвЂ™une portГ©e et dвЂ™une profondeur exceptionnelles. Nous sommes prГ©sentement Г la recherche d'un Scientifique des donnГ©es (В« Data Scientist В») pour se joindre Г notre Г©quipe. Le candidat idГ©al devrait ГЄtre passionnГ© par la recherche de pointe et les services analytiques pour les entreprises Fortune 500, les entreprises pharmaceutiques et biotechnologiques mondiales et les chefs de file dans des secteurs de la finance, l'Г©nergie et les sciences de la vie. Le Scientifique des donnГ©es sera un membre contributeur aux mandats des clients et aura l'occasion de travailler avec notre rГ©seau d'experts et de leaders d'opinion de classe mondiale. Description du poste et des responsabilitГ©s Le scientifique des donnГ©es aidera Г dГ©velopper, maintenir et enseigner de nouveaux outils et mГ©thodologies liГ©s Г la science des donnГ©es (В« Data Science В») et au HPC. Ce poste aidera Г©galement le Groupe d'analyse Г maintenir sa position de chef de file en ce qui a trait Г l'avancement de la mГ©thodologie et de l'analyse des donnГ©es. Le scientifique des donnГ©es sera chargГ© de se tenir au courant des nouveaux dГ©veloppements technologiques liГ©s Г la science des donnГ©es, afin de les partager plus largement avec le Groupe d'analyse. Les principales responsabilitГ©s de ce poste comprendront: - Collaborer avec les consultants pour relever les dГ©fis de la science des donnГ©es et de sciences informatiques - Agir Г titre de ressource et participer aux mandats et Г la recherche en tant que membre de l'Г©quipe de projet - Maintenir Г jour les connaissances sur les outils informatiques, fournir une formation technique et aider Г dГ©velopper la base de connaissances interne, notamment dans un environnement Linux - PrГ©senter la recherche Г des confГ©rences choisies Exemples de tГўches du scientifique des donnГ©es : - DГ©veloppement de systГЁmes de production en ingГ©nierie des donnГ©es ainsi quвЂ™en apprentissage machine pour des projets de science des donnГ©es full stack - Utiliser des mГ©thodologies NLP pour travailler avec les donnГ©es mГ©dicales Г©lectroniques, les donnГ©es des mГ©dias sociaux et d'autres donnГ©es non structures - Optimiser les procГ©dures de gestion et d'accГЁs aux grandes bases de donnГ©es (ex. rГ©clamations d'assurance, dossiers de santГ© Г©lectroniques, transactions financiГЁres) - CrГ©ation de portails d'analyse interactifs et de visualisations de donnГ©es (par exemple, en utilisant R/Shiny, Python/Flask, D3) - Construire et maintenir des outils de calcul de haute performance (HPC). - DГ©veloppement et rГ©vision de codes en R, Python et autres langages - Mise en place de procГ©dures optimisГ©es pour les tГўches rГ©pГ©titives ou intensives en calcul (C, C++, Cuda-C) Qualifications requises - Solides rГ©fГ©rences et expГ©rience dans la gestion de bases de donnГ©es et de la visualisation de donnГ©es - ExpГ©rience de travail significative dans un environnement Linux requise - ExpГ©rience antГ©rieure en statistique/Г©conomГ©trie ou bio-statistique - IdГ©alement, ГЄtre titulaire d'un doctorat en sciences informatiques, en mathГ©matiques, en statistique, en Г©conomie ou d'un autre diplГґme scientifique pertinent et possГ©der une expГ©rience pertinente. Les candidats ayant au moins un an d'expГ©rience dans le domaine peuvent Г©galement ГЄtre considГ©rГ©s. - Excellentes aptitudes de communication Г©crite et verbale - ExpГ©rience de projet avec R et/ou Python - FamiliaritГ© avec l'informatique en ligne/info nuagique et le stockage (AWS) - ExpГ©rience de travail dГ©montrГ©e au sein d'Г©quipes de projet et de collaboration avec d'autres personnes В­ Equal Opportunity Employer/Protected Veterans/Individuals with Disabilities. Please view Equal Employment Opportunity Posters provided by OFCCP here. The contractor will not discharge or in any other manner discriminate against employees or applicants because they have inquired about, discussed, or disclosed their own pay or the pay of another employee or applicant. However, employees who have access to the compensation information of other employees or applicants as a part of their essential job functions cannot disclose the pay of other employees or applicants to individuals who do not otherwise have access to compensation information, unless the disclosure is (a) in response to a formal complaint or charge, (b) in furtherance of an investigation, proceeding, hearing, or action, including an investigation conducted by the employer, or (c) consistent with the contractor's legal duty to furnish information. 41 CFR 60-1.35(c) | E4: 3.8 | F4: Analysis Group 3.8 | G4: Boston, MA | H4: Boston, MA | I4: 1001 to 5000 employees | J4: 1981 | K4: Private Practice / Firm | L4: Consulting | M4: Business Services | N4: $100 to $500 million (USD) | O4: -1
A5: 3 | B5: Data Scientist | C5: $137K-$171K (Glassdoor est.) | D5: JOB DESCRIPTION: Do you have a passion for Data and Machine Learning? Do you dream of working with customers on their most forward-looking AI initiatives? Does the challenge of developing modern machine learning solutions to solve real-world manufacturing problems exciting to you? We develop software for monitoring semiconductor manufacturing process and are looking to leverage the latest technologies to address our customer's needs. You will be part of a team that investigates and builds solutions based all the data available in factories, ranging from time series data, to post manufacturing data, to production logs. You will be working side by side with application developers and customers on real world problems with actual manufacturing data. JOB FUNCTION: Basic and applied research in statistical machine learning, deep learning, and data science as well as signal and information processing to advance the state of the art in time series analysis of semiconductor manufacturing data. Responsibilities: Perform data analysis, data pre-processing, and feature engineering in support of advanced machine learning algorithm development. Incorporate physical and operational insights/constraints into statistical models to achieve a high degree of robustness. Prototype algorithms for proof of concept, validation, and software implementation. Support performance evaluations and the transition of algorithms into existing fault detection and classification systems. Convey the results of scientific research to sponsors and the scientific community through briefings, conferences and peer-reviewed publications. Other related functions as assigned. REQUIRED QUALIFICATIONS: Bachelor's degree in computer science or chemical engineering or related technical field. Demonstrated ability in machine learning/artificial intelligence (ML/AI) development and/or scientific modelling and data analysis. Demonstrated ability with python/MATLAB or similar abstract language. Experience with both traditional ML and modern deep learning approaches. Experience with agile development practices and Git version control. Experience with one or more of the DNN frameworks like TensorFlow, PyTorch, Chainer. Experience with SQL, Graph stores, or NoSQL stores. Applicant must have a dynamic skill set, be willing to work with new technologies, be highly organized and capable of planning and coordinating multiple tasks. The position will require attention to detail, effective problem solving skills and excellent judgment. Ability to work independently with sensitive and confidential information, maintain a professional demeanor, work as a team member without daily supervision. COMPENSATION & BENEFITS: Compensation will be commensurate with experience including a competitive base salary, bonus opportunity, competitive benefits package, and relocation assistance. INFICON, is committed to ensuring that our online application process provides an equal opportunity to all job seekers that apply without regard to race, religion, ethnicity, national origin, citizenship, gender, age, protected veteran status, disability status, genetic information, sexual orientation, or any other protected characteristic. A notice describing Federal equal employment opportunity laws is available here and here to reaffirm this commitment. PI120660357 | E5: 3.5 | F5: INFICON 3.5 | G5: Newton, MA | H5: Bad Ragaz, Switzerland | I5: 501 to 1000 employees | J5: 2000 | K5: Company - Public | L5: Electrical & Electronic Manufacturing | M5: Manufacturing | N5: $100 to $500 million (USD) | O5: MKS Instruments, Pfeiffer Vacuum, Agilent Technologies
A6: 4 | B6: Data Scientist | C6: $137K-$171K (Glassdoor est.) | D6: Data Scientist Affinity Solutions / Marketing Cloud seeks smart, curious, technically savvy candidates to join our cutting-edge data science team. We hire the best and brightest and give them the opportunity to work on industry-leading technologies. The data sciences team at AFS/Marketing Cloud build models, machine learning algorithms that power all our ad-tech/mar-tech products at scale, develop methodology and tools to precisely and effectively measure market campaign effects, and research in-house and public data sources for consumer spend behavior insights. In this role, you'll have the opportunity to come up with new ideas and solutions that will lead to improvement of our ability to target the right audience, derive insights and provide better measurement methodology for marketing campaigns. You'll access our core data asset and machine learning infrastructure to power your ideas. Duties and Responsibilities В· Support all clients model building needs, including maintaining and improving current modeling/scoring methodology and processes, В· Provide innovative solutions to customized modeling/scoring/targeting with appropriate ML/statistical tools, В· Provide analytical/statistical support such as marketing test design, projection, campaign measurement, market insights to clients and stakeholders. В· Mine large consumer datasets in the cloud environment to support ad hoc business and statistical analysis, В· Develop and Improve automation capabilities to enable customized delivery of the analytical products to clients, В· Communicate the methodologies and the results to the management, clients and none technical stakeholders. Basic Qualifications В· Advanced degree in Statistics/Mathematics/Computer Science/Economics or other fields that requires advanced training in data analytics. В· Being able to apply basic statistical/ML concepts and reasoning to address and solve business problems such as targeting, test design, KPI projection and performance measurement. В· Entrepreneurial, highly self-motivated, collaborative, keen attention to detail, willingness and capable learn quickly, and ability to effectively prioritize and execute tasks in a high pressure environment. В· Being flexible to accept different task assignments and able to work on a tight time schedule. В· Excellent command of one or more programming languages; preferably Python, SAS or R В· Familiar with one of the database technologies such as PostgreSQL, MySQL, can write basic SQL queries В· Great communication skills (verbal, written and presentation) Preferred Qualifications В· Experience or exposure to large consumer and/or demographic data sets. В· Familiarity with data manipulation and cleaning routines and techniques. | E6: 2.9 | F6: Affinity Solutions 2.9 | G6: New York, NY | H6: New York, NY | I6: 51 to 200 employees | J6: 1998 | K6: Company - Private | L6: Advertising & Marketing | M6: Business Services | N6: Unknown / Non-Applicable | O6: Commerce Signals, Cardlytics, Yodlee
A7: 5 | B7: Data Scientist | C7: $137K-$171K (Glassdoor est.) | D7: About Us: Headquartered in beautiful Santa Barbara, HG Insights is the global leader in technology intelligence. HG Insights uses advanced data science methodologies to help the world's largest technology firms and the fastest growing companies accelerate their sales, marketing, and strategy efforts. We offer a casual yet professional environment. Get your sweat on at one of our fitness classes or go for a run along the beach which is two blocks away. You can find employees riding bikes to lunch in the funk zone or hanging out in one of our collaboration spaces. We are passionate about our jobs with a get-it-done attitude, yet we don't take ourselves too seriously. What You'll Do: We are looking for a data scientist with software development or data engineering background to join our research team which reports directly to the CTO. We are a rapidly growing company with small focused engineering teams that deliver innovative features to a fast growing market. We build big-data systems utilizing cutting edge technologies and solutions that allow for our engineers to continuously learn and develop while shipping amazing products. Qualities/ Experience: Self-learner, hacker, technology advocate who can work on anything Amazing engineering skills, you're on your way to being the one of the best engineers you know You can architect, design, code, test, and mentor others Experience working with interesting and successful projects Thrive in a fast growing environment Excellent written and spoken English communication An interest in Machine Learning and Natural Language Processing What You'll Be Responsible For: Build solutions for text classification, entity linking, and entity extraction and other related projects Scaling machine learning and NLP projects to run against large datasets in virtualized environments. You will collaborate with Product Development Teams to build the most effective solutions You will develop features in our databases, backend apps, front end UI, and Data as a Service (DAAS) product You will help architect and design large scale enterprise big-data systems You will work on ideas from different team members as well as your own Fix bugs rapidly Attend daily stand-up meetings, planning sessions, encourage others, and collaborate at a rapid pace What You'll Need: BS, MS, or Ph.D. in Computer Science or related technical discipline Experience Natural Language Processing, preferably in a commercial setting. Experience building Logistic Regression Models Proficient in Python and Jupyter as well as related data science libraries (such as Scikit-learn, NLTK, SpaCy, Tensorflow) Proficient in Java or Scala (3+ years experience recommended) Experience with MySQL, ElasticSearch, ESB, Hadoop, Spark, or other related data processing/database technologies Experience with Amazon Web Services (EC2, S3, RDS, EMR, ELB, etc.) Experience with web services using REST in Java Actual coding experience in large distributed environments with multiple endpoints and complex interactions Comfortable in an agile development environment Understanding and have real world experience using design patterns Comfortable programming on a Mac with Intellij and other tools HG Insights Company is an Equal Opportunity Employer Please note that HG Insights does not accept unsolicited resumes from recruiters or employment agencies. In the event of a recruiter or agency submitting a resume or candidate without a signed agreement being in place, we explicitly reserve the right to pursue and hire such candidates without any financial obligation to the recruiter or agency. Any unsolicited resumes, including those submitted directly to hiring managers, are deemed to be the property of HG Insights | E7: 4.2 | F7: HG Insights 4.2 | G7: Santa Barbara, CA | H7: Santa Barbara, CA | I7: 51 to 200 employees | J7: 2010 | K7: Company - Private | L7: Computer Hardware & Software | M7: Information Technology | N7: Unknown / Non-Applicable | O7: -1
A8: 6 | B8: Data Scientist / Machine Learning Expert | C8: $137K-$171K (Glassdoor est.) | D8: Posting Title Data Scientist / Machine Learning Expert 04-Feb-2020 Job ID 288341BR Job Description ONE Global Discovery Chemistry Community working across 7 disease areas at the Novartis Institutes for BioMedical Research (NIBR) is seeking a highly talented and motivated Data Scientist to join our Global Discovery Chemistry Department in Cambridge, MA. The successful candidate will join an energizing and collaborative research organization, working alongside colleagues who are committed to improving human health through the discovery of transformative medicines. We are seeking a unique data scientist with the skills, experience and passion to extract new knowledge and disruptive insights from the large and rich body of data collected by one of the worldвЂ™s leading pharmaceutical companies. You will be a member of our global Computer-Aided Drug Discovery (CADD) group, an interdisciplinary team of expert molecular modelers, cheminformaticians, and data scientists. Teamed up with domain experts from biology, chemistry and translational medicine, this is a unique opportunity to develop and apply cutting-edge machine learning technologies to uncover insights to real-world drug discovery problems and innovate paths to new medicines. Your responsibilities include: вЂўDevelop and implement methods for extracting patterns and correlations from both internal and external data sources using machine learning toolkits вЂўDevelop workflows for conducting comparative analysis among NovartisвЂ™ diverse data sources as well as generalizing approaches developed in-house or externally. вЂўEnable open-source solutions for internal use and implement cutting-edge published scientific methods. вЂўDevelop customized machine learning solutions including data querying and knowledge extraction. вЂўInteract and be part of interdisciplinary project teams to drive effective decision-making by mining and developing predictive models вЂўDevelop new skills in the area of cheminformatics and drug discovery and leverage those to accelerate development of new machine learning algorithms вЂўKeep ahead of scientific literature and interact with internal and external scientists to integrate novel data science technologies Minimum requirements Education: Advanced degree (M.Sc. or higher) in data science and machine learning, statistics, computer sciences, cheminformatics, mathematics, computational chemistry, computational biology, bioinformatics, or related field. Minimum experience & skills: вЂўIn-depth experience with modern and classical machine learning methods вЂўStrong statistical foundation with broad knowledge of supervised and unsupervised techniques вЂўProgramming experience (preferred Python, R, C++) preferably in Linux and high-performance computing environments вЂўGood listener - strong, concise, and consistent written and oral communication вЂўTalent for communicating stories through data visualizations вЂўProven ability to collaborate with others вЂўA passion for tackling challenging problems and developing creative solutions вЂўA drive for self-development with a focus on scientific know-how Additional qualifications that will help in the role: вЂўDemonstrated impact using machine learning libraries, such as scikit-learn, PyTorch or similar in a cheminformatics context вЂўHands on experience with data analysis software such as Spotfire, R-shiny or similar вЂўWorking experience with open-source cheminformatics toolkits such as RDKit вЂўWorking experience with source-code management systems such as Git/github/bitbucket вЂўFamiliar with the foundational concepts in molecular biology, pharmacology or medicine. Working knowledge of medicinal chemistry and drug discovery is a plus Why consider Novartis? 750 million. ThatвЂ™s how many lives our products touch. And while weвЂ™re proud of that fact, in this world of digital and technological transformation, we must also ask ourselves this: how can we continue to improve and extend even more peopleвЂ™s lives? We believe the answers are found when curious, courageous and collaborative people like you are brought together in an inspiring environment. Where youвЂ™re given opportunities to explore the power of digital and data. Where youвЂ™re empowered to risk failure by taking smart risks, and where youвЂ™re surrounded by people who share your determination to tackle the worldвЂ™s toughest medical challenges. We are Novartis. Join us and help us reimagine medicine. Job Type Full Time Country USA Work Location Cambridge, MA Functional Area Research & Development Division NIBR Business Unit Global Discovery Chemistry Employment Type Regular Company/Legal Entity NIBRI EEO Statement The Novartis Group of Companies are Equal Opportunity Employers and take pride in maintaining a diverse environment. We do not discriminate in recruitment, hiring, training, promotion or any other employment practices for reasons of race, color, religion, gender, national origin, age, sexual orientation, marital or veteran status, disability, or any other legally protected status. Shift Work No | E8: 3.9 | F8: Novartis 3.9 | G8: Cambridge, MA | H8: Basel, Switzerland | I8: 10000+ employees | J8: 1996 | K8: Company - Public | L8: Biotech & Pharmaceuticals | M8: Biotech & Pharmaceuticals | N8: $10+ billion (USD) | O8: -1
A9: 7 | B9: Data Scientist | C9: $137K-$171K (Glassdoor est.) | D9: Introduction Have you always wanted to run experiments on a global fleet of consumer robots? iRobot is looking for a data scientist to help manage a/b tests related to robot software, track performance KPIs, and share results with software teams. A strong candidate has experience in experimental design, hypothesis testing, and statistics, in addition to strong SQL and Python skills. What You Will Do: Guide software and product management teams in designing rigorous experiments to test the impact of new software versions. Dashboarding to monitor results live from the fleet. Test hypotheses about software performance using appropriate statistical methods. Develop metrics to track software performance. Uphold scientific best practices in experimental design and cohort selection. Contribute to a management system for cohort selection. To Be Successful You Will Have: At least 1 year of relevant job, internship, or co-op experience. M.S. in computer science, statistics, mathematics, physics, chemistry, biology, or social sciences is a plus. Very detail-oriented and eager to get your hands dirty in the data. Proficient in Python, SQL, and data visualization, with experience using pandas, numpy, sklearn, scipy, matplotlib, or plotly. Experienced in designing experiments, making and testing hypotheses, and identifying the appropriate metrics to answer a question. Savvy in statistical methods and able to select the right test for each situation. Can balance business considerations with the need for scientific rigor. Self-motivated and comfortable working in a fast-paced, delivery-focused environment. Skilled communicator who can make the complicated seem simple. Passionate about using data to drive decision-making! | E9: 3.5 | F9: iRobot 3.5 | G9: Bedford, MA | H9: Bedford, MA | I9: 1001 to 5000 employees | J9: 1990 | K9: Company - Public | L9: Consumer Electronics & Appliances Stores | M9: Retail | N9: $1 to $2 billion (USD) | O9: -1
A10: 8 | B10: Staff Data Scientist - Analytics | C10: $137K-$171K (Glassdoor est.) | D10: Intuit is seeking a Staff Data Scientist to cover Intuits Consumer Group (TurboTax, Mint, Turbo). We have an exciting opportunity to help shape how we use data to generate hypotheses, surface insights, and build models in order to personalize customer experiences and provide awesome outcomes for the business and our customers. This role will partner closely with data engineering, data analytics, data science, marketing managers, and product management. | E10: 4.4 | F10: Intuit - Data 4.4 | G10: San Diego, CA | H10: Mountain View, CA | I10: 5001 to 10000 employees | J10: 1983 | K10: Company - Public | L10: Computer Hardware & Software | M10: Information Technology | N10: $2 to $5 billion (USD) | O10: Square, PayPal, H&R Block
A11: 9 | B11: Data Scientist | C11: $137K-$171K (Glassdoor est.) | D11: Ready to write the best chapter of your career? XSELL Technologies is an artificial intelligence company focused on increasing sales. Our cloud-based machine learning engine uses predictive analytics and natural language processing to equip sales professionals with the best real-time responses, driving improved conversion rates and customer experiences. We pride ourselves on our high performing, collaborative culture. We are passionate about our product, our clients, and our industry leading results. XSELL is currently seeking a Data Scientist to serve as a key member of our Data Science team. This role will work within the SAFe Agile framework of continuous delivery, work with other Data Scientists, and be a critical resource for our growing Data Science staff. Job Description Designing, implementing and improving XSELLвЂ™s proprietary softwares, real time messaging recommendation systems, HiPerCoBot and QABOt using various mathematical, Natural Language Processing (NLP) algorithms and machine learning models. Developing new systems using Python NLP (lemmatization, stemming, named entity recognition) and updating the existing systems by adding new features to enhance the customers experience. Interacting with stakeholders to identify the requirements and define new processes. Closely work with the team to define the architecture of the Microservice environment and deploy systems using RESTful APIвЂ™s. Planning, development, and analysis of dialogue prediction/sentiment models, causal models of customer/agent behavior. Improving the accuracy of the in house XSELL Recommendation System software suite by evaluating and monitoring annotations manually labelled by Ontology team. Analyzing and researching the current market trends for possible AI opportunities/improvements. Qualifications MS/PhD in a quantitative discipline (e.g. Machine Learning, Data Science, Computer Science, Mathematics, Statistics, or a related field). 3+ years full time employment or postdoctoral experience building and validating predictive models on structured or unstructured data. Proficiency in Python with knowledge of basic libraries for data manipulation, machine learning, natural language processing and text mining. Experience creating and using advanced machine learning algorithms (regression, neural networks, etc.) Understanding of deep learning algorithms and experience with related libraries such as TensorFlow, PyTorch. Nice to Have Experience in SQL. Understanding of object oriented design. Ability to craft new concepts and stay current with academic research Experience with graph databases and graph designs. Experience in designing/developing production level machine learning architectures (using Flask or Redis) We provide competitive compensation, generous benefits, and a professional atmosphere. XSELL fosters an entrepreneurial, results driven work environment where you will have the opportunity to be part of a collaborative, inclusive team and be able to grow and develop your professional career. XSELL Technologies is an Equal Employment Opportunity Employer and all employment decisions shall be made without regard to age, race, creed, color, religion, sex, national origin, ancestry, disability status, veteran status, sexual orientation, gender identity or expression, genetic information, marital status, citizenship status or any other basis as protected by federal, state, or local law. Location: Chicago, IL Role: Full-Time / Salaried | E11: 3.6 | F11: XSELL Technologies 3.6 | G11: Chicago, IL | H11: Chicago, IL | I11: 51 to 200 employees | J11: 2014 | K11: Company - Private | L11: Enterprise Software & Network Solutions | M11: Information Technology | N11: Unknown / Non-Applicable | O11: -1
A12: 10 | B12: Data Scientist | C12: $137K-$171K (Glassdoor est.) | D12: Join our team dedicated to developing and executing innovative solutions in support of customer mission success. Job Description: Novetta is seeking a Data Scientist who wants to develop innovative solutions for customers and internal product teams. We look to rapidly prototype solutions and deploy the most promising of them. We identify and leverage the latest techniques (fast.ai is a team favorite) so that our customers can stay one step ahead. On every project you'll learn something new (and likely teach us something as well). If that sounds appealing to you - we'd love to chat. Responsibilities include: Develop solutions spanning multiple subject areas, from NLP to Image and Video. Maintain awareness of state-of-the-art machine learning and techniques, methods and platforms, including commercial and open source. Implement, configure and test machine learning and deep learning libraries and platforms (e.g. fast.ai, TensorFlow, Keras, XGBoost, LightGBM). Test solutions on AWS using services such as SageMaker, EC2, and Snowball Edge. Write blog posts and presentations that clearly communicate complex machine learning concepts to both technical and non-technical audiences. Contribute to visually-appealing, web-enabled prototype applications that illustrate relevant machine learning capabilities. Basic Qualifications: Experience with Python Experience with machine learning or statistics Ability to work both independently and collaboratively. High levels of curiosity, creativity, and problem-solving capabilities. Strong written and verbal communication skills. Comfortable navigating the command line. Desired Skills: Research experience in Machine Learning specific to Natural Language Processing, Computer Vision, or deep learning. Experience with managing data and creating algorithms using AWS. Experience with R, Java, or other programming languages. Security Clearance: Must be eligible to obtain and maintain a TS/SCI with Poly clearance Novetta, from complexity to clarity. Novetta delivers highly scalable advanced analytics and secure technology solutions to address challenges of national and global significance. Focused on mission success, Novetta pioneers disruptive technologies in machine learning, data analytics, full-spectrum cyber, cloud engineering, open source analytics, and multi-INT fusion for Defense, Intelligence Community, and Federal Law Enforcement customers. Novetta is headquartered in McLean, VA with over 1,000 employees across the U.S. Our culture is shaped by a commitment to our core values: Integrity вЂў We hold ourselves accountable to the highest standards of integrity and ethics. Customer Success вЂў We strive daily to exceed expectations and achieve customer mission success. Employee Focus вЂў We invest in our employees' professional development and training, respecting individuality and fostering a culture of diversity and inclusion. Innovation вЂў We know that discovering new and innovative ways to solve problems is critical to our success and makes us a great company. Excellence in Execution вЂў We take pride in flawless execution as we build a company that is best in class. Earn a REFERRAL BONUS for the qualified people you know. For more details or to submit a referral, visit bit.ly/NovettaReferrals. Novetta is an equal opportunity/affirmative action employer. All qualified applicants will receive consideration for employment without regard to sex, gender identity, sexual orientation, race, color, religion, national origin, disability, protected veteran status, age, or any other characteristic protected by law. | E12: 4.5 | F12: Novetta 4.5 | G12: Herndon, VA | H12: Mc Lean, VA | I12: 501 to 1000 employees | J12: 2012 | K12: Company - Private | L12: Enterprise Software & Network Solutions | M12: Information Technology | N12: $100 to $500 million (USD) | O12: Leidos, CACI International, Booz Allen Hamilton
A13: 11 | B13: Data Scientist | C13: $137K-$171K (Glassdoor est.) | D13: About Us Interested in working for a human-centered technology company that prides itself on using modern tools and technologies? Want to be surrounded by intensely curious and innovative thinkers? Seeking to solve complex technical challenges by building products that work for people, meet and exceed the needs of businesses, and work elegantly and efficiently? Modeling ourselves after the 1904 World's Fair, which brought innovation to the region, 1904labs is seeking top technical talent in St. Louis to bring innovation and creativity to our clients. Our clients consist of Fortune 500 and Global 2000 companies headquartered here in St. Louis. We partner with them on complex projects that range from reimagining and refactoring their existing applications, to helping to envision and build new applications or data streams to operationalize their existing data. Working in a team-based labs model, using our own flavor of #HCDAgile, we strive to work at the cutting edge of technology's capabilities while solving problems for our clients and their users. The Role As a Data Scientist with 1904labs, you will be working with other data scientists, data engineers, and developers to provide analytical services to clients. You will leverage the clients' data assets to answer business questions using best practices and innovative approaches. This will mean employing various data science tools (Python, apache spark, TensorFlow) and techniques (dimensionality reduction, unsupervised learning, supervised learning) to create and test machine learning algorithms. Once tested and verified you will work with development teams to implement the algorithm as a scalable, hosted service. We're looking for an experienced and creative data scientist who can conceptualize a project from start to finish, identifying the appropriate data and methodologies to use. Our Data Scientists work with open-source machine learning packages and libraries, so this position involves building custom ML/AI utilities from open-source resources in languages such as Python (preferred) and R. In this role, you will own and share technical solutions with both technical and non-technical stakeholders across multiple teams both internally and with external clients. Responsibilities Perform data analysis to understand the right combinations of data to meet outlined objectives Translate client queries into actionable data pulls and help translate outputs into client strategies Build and evaluate predictive modeling & machine learning utilities to produce meaningful outcomes that enable data-led decisions Translate analysis results into actionable insights Present insights to both technical and non-technical audiences Partner with internal data scientists, developers, and tech teams to develop new methodologies and utilities Work with development teams to implement data science algorithms as scalable, hosted services Your Skills Requirements Background in math including linear algebra, statistics, probability, and numerical analysis. Machine Learning Analysis: Must be able to execute, evaluate, and apply various models such as logistic regression, random forests/decision tree, nearest neighbor, neural net, support vector machine, an ensemble of multiple models, etc Programming: Proficient coding in a language suited for machine learning systems such as Python or R (not reliant on GUI-based systems to execute analysis) for the purpose of cleaning, manipulating, visualizing, and analyzing data Desired Skills Experience with software engineering and developing deployable API services Must be adaptable and have the drive to learn new technologies and frameworks to support developing client solutions Using browser based interactive computational environments (like Jupyter Notebook) to perform analysis activities and test / evaluate data models and algorithms. Tools: Spark, Pandas, SciKit-Learn, TensorFlow, Keras, SQL Communication: Must be able to explain analysis process and translate results into actionable insights for both technical and non-technical audiences Teamwork: Must be accountable for individual responsibilities while working collaboratively with development and engineering teams to achieve project deliverables Comfort in an agile development environment (eg. writing stories, participating in workshops, sprint planning and retros) Perks Benefits Program (medical, dental, life insurance, 401(k), professional and personal development, PTO) Innovation Time - we allow 10% of your time to be devoted to innovation hours. This time can be used to foster individual ideas, personal projects, start up ideas, improve an open source tool or for career advancement and self-education. All during traditional working hours. Dress Code - we don't have one These roles are located in St. Louis, MO. While we would prefer local candidates your location is not the most important factor; please help us understand why you would like to call St. Louis home if you would be relocating. ]]> | E13: 4.7 | F13: 1904labs 4.7 | G13: Saint Louis, MO | H13: Saint Louis, MO | I13: 51 to 200 employees | J13: 2016 | K13: Company - Private | L13: IT Services | M13: Information Technology | N13: Unknown / Non-Applicable | O13: Slalom, Daugherty Business Solutions
A14: 12 | B14: Data Scientist - Statistics, Early Career | C14: $137K-$171K (Glassdoor est.) | D14: *Organization and Job ID** Job ID: 310918 Directorate: National Security Directorate Division: Computing & Analytics Group: Applied Statistics & Computational Modeling *Job Description** This position is for a Scientist in Data Science and Applied or Mathematical Statistics who will provide scientific and technical research within the National Security Directorate (NSD) supporting the data analytics capabilities of the Computational Analytics Division. The Scientist will develop and apply fundamental mathematical or statistical theory to advance analytic solutions in various scientific domains. The Scientist must be able to draw from a strong statistical background, in areas including experimental design, advanced statistical modeling (e.g. mixed linear models, nonparametric models, etc.), machine learning, and computer simulations, to recognize patterns, characterize uncertainty, and develop predictive models using structured and unstructured data. The Scientist will produce solutions driven by domain science and mathematical statistical science from complex and high-dimensional datasets and design, develop, and evaluate advanced algorithms that lead to optimal value extraction from data. In addition to technical research this position expects participation and career development in task management, proposal writing, business development, and publishing. Operating on the data-information-knowledge continuum, staff at PNNL employ diverse methods to confront significant problems of national interest from distilling distributed data into knowledge that supports decision processes to enabling resilient technologies that enhance computing at extreme scales. Our research portfolio spanning from basic to applied includes statistical modeling and experimental design, applied statistics, applied mathematics, machine learning, operations research, optimization, and other advanced statistical and mathematical domains. Computing researchers and practitioners work side by side to apply advanced theories, methods, algorithms, models, evaluation tools and testbeds, and computational-based solutions to address complex scientific challenges affecting energy, biological sciences, the environment, and national security. Core domain knowledge is beneficial, such as in the nuclear, biological, energy, materials, or chemical science spaces. *The hiring level will be determined based on the education, experience, and skill set of the successful candidate based on the following:** *Level II** : Leads specific tasks of the project to meet scope, schedule and budget. Expected to contribute professionally, building a professional reputation for technical expertise. Fully applying and interpreting standard theories, principles, methods, tools and technologies. Contributes technical content to proposals and develops business through excellent project performance. *Level III:** Manages small to moderate projects and/or major project tasks. Integrates intellectual and technical capabilities of work teams. Enhances technical/professional skills of junior staff through active mentoring and training. Generates ideas for new proposals and participates in business development activities *Minimum Qualifications** + BS/BA with 2 years of experience, MS/MA with 0 years of experience, or PhD with 0 years of experience *Preferred Qualifications** + BS/BA with 5 years of experience, MS/MA with 3 years of experience, or PhD with 1 year of experience, focused in statistics with experience involving increasing levels of scientific research, task management, and programmatic responsibility + Position requires ability to apply theories and develop technical approaches with minimal oversight + Position requires the ability to effectively team with scientists and engineers to develop creative solutions to complex problems *Equal Employment Opportunity** Battelle Memorial Institute (BMI) at Pacific Northwest National Laboratory (PNNL) is an Affirmative Action/Equal Opportunity Employer and supports diversity in the workplace. All employment decisions are made without regard to race, color, religion, sex, national origin, age, disability, veteran status, marital or family status, sexual orientation, gender identity, or genetic information. All BMI staff must be able to demonstrate the legal right to work in the United States. BMI is an E-Verify employer. Learn more at jobs.pnnl.gov. *_Please be aware that the Department of Energy (DOE) prohibits DOE employees and contractors from participation in certain foreign government talent recruitment programs. If you are offered a position at PNNL and are currently a participant in a foreign government talent recruitment program you will be required to disclose this information before your first day of employment._** *Other Information** Due to business needs and client space, US Citizenship is required: The Pacific Northwest National Laboratory is subject to the Department of Energy Unclassified Foreign Visits & Assignment Program site, information, technologies, and equipment access requirements. _Directorate:_ _National Security_ _Job Category:_ _Scientists/Scientific Support_ _Group:_ _Appld Stats & Comp Modeling_ _Opening Date:_ _2020-06-03_ _Closing Date:_ _2020-09-01_ | E14: 3.7 | F14: PNNL 3.7 | G14: Richland, WA | H14: Richland, WA | I14: 1001 to 5000 employees | J14: 1965 | K14: Government | L14: Energy | M14: Oil, Gas, Energy & Utilities | N14: $500 million to $1 billion (USD) | O14: Oak Ridge National Laboratory, National Renewable Energy Lab, Los Alamos National Laboratory
A15: 13 | B15: Data Modeler | C15: $137K-$171K (Glassdoor est.) | D15: POSITION PURPOSE: The Data Architect/Data Modeler will be part of the OWI Analytic team. Our team works closely with our business partners, proactively developing and delivering analytic solutions.The Primary Deliverables include: Data architecture, data workflow logical models, physical source data models, data profiling reports and data audits, data definitions, data taxonomy, data metrics, meta-data, data lineage, data cleansing services. Functions of our data team is to development and design, data quality management, reference and master data management, data integration, data governance. OWI is a fast-paced and dynamic organization. Individuals will be handling multiple activities in a team as well as individual contributor environment. DUTIES, TASKS, AND RESPONSIBILITIES: В·Activities: data modeling, data audit, detailed data design, define rules, establish master data solutions, define hierarchies, distribute reference and master data, profile, analyze, assess data quality, design data quality management procedures, clean and correct data quality defects, establish data governance. В·Experienced utilizing HANA studio data modeler which should include initial setup, calculations and, calculation and analytical views, data base schemas, creating attribute user/role creation. В·Setting up security, Analytic privileges, user integration services, SQL script, SLT, SDA, SDI and HANA Live solution models. В·Demonstrate critical thinking, analytical skills, and employ judgment to offer thoughtful, concise input toward resolutions of problems. В·Assist team building the BW4HANA modeler including standard and custom development and deployment of EWD design building BW objects e.g. Composite Providers, Advanced DSOвЂ™s, ODS Views, Data Sources, Data Loading using SLT. В·Be able to translate data requirements into business processes and reverse engineer business processes into data requirements Comprehension of DevOps and Agile development and application to data centric architecture and solutions В·Leadership skills needed to successfully promote ideas, coordinate work activities, and plan deliverables within a project team. SKILLS, KNOWLEDGE, AND ABILITIES: В·Advanced expert database handling languages (SQL and variants) В·Expert in data modeling (physical and logical), ER diagrams, data dictionary, data map, normalize de-normalize, agile data modeling В·Practical skill sets in BI and Data visualization tools В·Knowledge of other programming languages and ability to write code (i.e. VBA, python, XML) В·Working knowledge of ETL В·Working knowledge of SAP В·Basic Project Management and Business Process modeling В·Minimum BachelorвЂ™s Degree in Engineering Technology, Computer Science, or closely related field. В·A minimum of 3 yearsвЂ™ experience in SAP Data Management and Governance, SAP Data Services (Data Extract, Data Profiling, de-duplication) В·Advanced competency in SAP HANA, SQL Server Database, Tableau and Alteryx В·Experience in transactional modeling and dimensional data warehouse model development with at least 4 years developing in HANA. В·Work with other IM data modelers and ETL developers to design data loads into HANA В·Excellent verbal and written communication skills with a strong focus on the ability to clearly articulate and discuss technical issues with both technical and business personnel. В·Bachelor degree in Computer Science, Math or a related IT field or equivalent work experience in an IT field required В·Strong analytical skills, able to effectively solve problems in a timely manner | E15: 3.1 | F15: Old World Industries 3.1 | G15: Northbrook, IL | H15: Northbrook, IL | I15: 201 to 500 employees | J15: 1973 | K15: Company - Private | L15: Chemical Manufacturing | M15: Manufacturing | N15: $1 to $2 billion (USD) | O15: -1
A16: 14 | B16: Data Scientist | C16: $137K-$171K (Glassdoor est.) | D16: Position Description: Want to make a difference in our world. Mathematica applies expertise at the intersection of data, methods, policy, and practice to improve well-being around the world. We collaborate closely with public- and private-sector partners to translate big questions into deep insights that improve programs, refine strategies, and enhance understanding. Our work yields actionable information to guide decisions in wide-ranging policy areas, from health, education, early childhood, and family support to nutrition, employment, disability, and international development. We are looking for aData Scientist in our Washington DC office. Data scientists lead data processing and analysis tasks, such as monitoring data quality, developing documentation, applying statistical and data science methods, and creating data visualizations. Data scientists are expected to work on multi-disciplinary teams, overseeing and mentoring junior data scientists. The work of our data scientists supports our company's core offerings in program evaluation and data analytics, which yield crucial evidence and information for policy and decision makers. Data scientists contribute throughout the course of a project on tasks such as the following: Leading multidisciplinary teams to answer research questions or build solutions that involve linking health or healthcare data (e.g., Medicare claims or HCUP) to other administrative data (e.g., Hospital Compare files) Designing, planning, and overseeing the data science workflow on tasks and projects, involving descriptive statistics, machine learning or statistical analysis, data visualizations, and diagnostics using programming languages such as R or Python Communicating results to collaborative project teams using data visualizations and presentations using tools such as Markdown (e.g., R Markdown), notebooks (e.g., Jupyter or Databricks), or interactive visualizations (e.g., R Shiny or Dash). Developing and implementing systems to ingest, process, and manage datasets Developing and maintaining documentation using Atlassian Confluence and Jira Implementing quality assurance practices such as version control and testing Leading or supporting proposal sections or applications Position Requirements: Demonstrated enthusiasm for applying data science and statistics to social impact projects in academic, extra-curricular, and/or professional settings An excellent academic record, including courses in subjects such as statistics, data science, math, computer science, and/or social science, and the following credentials: PhD, or 3+ years of experience in a social policy field post Masters or immersive bootcamp (e.g., Metis) Mastery of R or Python to manipulate data, conduct analyses, and create data visualizations Ability and desire to work independently as part of remote, interdisciplinary teams Ability and desire to mentor junior data scientists and contribute to Mathematicas growing health data science community of 50+ staff Ability to version code using Git Strong oral and written communication skills. Nice-to-have Skills: Experience with reproducible research principles, interactive visualizations, tidyverse, AWS, Google Cloud Platform, R Shiny, R Markdown, pandas, healthcare claims and administrative data (e.g., Medicare, Medicaid, electronic health records, all-payer claims databases, HCUP), and/or scikit-learn. Please submit a cover letter, resume, and salary expectations. You will be asked to attach these materials during the online application process. Please click the "Apply Now" icon after the Position Description to attach your documents. Letter of recommendations not expected or required. Mathematica offers our employees competitive salaries and a comprehensive benefits package, as well as the advantages of being 100 percent employee-owned. As an employee stock owner, you will experience financial benefits of ESOP holdings that have increased in tandem with the companys growth and financial strength. You will also be part of an independent, employee-owned firm that is able to define and further our mission, enhance our quality and accountability, and steadily grow our financial strength. Various federal agencies with whom we contract require that staff successfully undergo a background investigation or security clearance as a condition of working on the project. If you are assigned to such a project, you will be required to obtain the requisite security clearance. We are an Equal Opportunity Employer and do not discriminate against any employee or applicant for employment because of race, color, sex, age, national origin, religion, sexual orientation, gender identity, status as a veteran, and basis of disability or any other federal, state or local protected class. | E16: 3.4 | F16: Mathematica Policy Research 3.4 | G16: Washington, DC | H16: Princeton, NJ | I16: 1001 to 5000 employees | J16: 1986 | K16: Company - Private | L16: Consulting | M16: Business Services | N16: $100 to $500 million (USD) | O16: -1
A17: 15 | B17: Experienced Data Scientist | C17: $137K-$171K (Glassdoor est.) | D17: *******Please Apply using this link: https://app.smartsheet.com/b/form/2cb8018ed6a041b0870e3cd056c286ab Our Focus In aviation safety, we seek to minimize the potential for harm to the flying public. To support this effort, we collect vast amounts of operational and simulation data. How can we use statistical analyses and data science to analyze this data and effect meaningful change to aviation safety? If this sounds interesting to you, GGTI seeks a Data Scientist to join its Data Science & Analytics Team. WhatвЂ™s the Job? В· Preprocessing, cleansing, and verifying integrity of data that can be provided as input for advanced analytics В· Ad-hoc analysis and presentations of results for technical and non-technical audiences В· Feature selection, model building and optimization using machine learning techniques В· Building regression, classification, association models В· Building anomaly detection systems About You You are an experienced Data Scientist with an advanced degree in a quantitative discipline. You will be able to discover information hidden in vast amounts of aviation data, including operation and simulated data, and provide recommendations to managements at various levels. Along with working with air traffic domain experts, you will be able to apply data mining techniques, perform statistical analyses, and build high quality predictive models and causal analyses of safety issues. You can analyze large, complex, multi-dimensional datasets with R and/or Python and Business Intelligence (BI) tools such as Tableau. In addition, you have some familiarity with SQL. What do you need to qualify? * В· 10+ years of professional work experience in a quantitative field В· A Ph.D. or MasterвЂ™s Degree in operations research, applied statistics, Computer Science (data mining, machine learning stream) or a related quantitative discipline В· Deep understanding of statistical and predictive modeling concepts, machine-learning approaches, clustering and classification techniques, and recommendation and optimization algorithms В· Excellent applied statistics skills, such as distributions, statistical testing, regression, etc. В· Excellent understanding of common machine learning techniques and algorithms, such as K-means, k-NN, Bayesian Networks, SVM, Decision trees, ensemble methods etc. В· Experience with common data science toolkits, such as Python, R, Weka, NumPy, MatLab, etc. Proficiency in at least one of these (preferably Python) В· Experience with data visualization tools, such as D3.js, Tableau etc. В· Experience with Amazon Web Services В· Some experience with NoSQL databases, such as MongoDB, Cassandra, or HBase В· Ability to pass a Federal Government background investigation to obtain a Public Trust clearance. В· Current U.S. Citizen/Green Card-holder Stand-out Skills Deep learning with TensorFlow, Torch, or similar Spark, Hadoop, or similar SQL, Java or C/C++. *******Please Apply using this link: https://app.smartsheet.com/b/form/2cb8018ed6a041b0870e3cd056c286ab | E17: 4.4 | F17: Guzman & Griffin Technologies (GGTI) 4.4 | G17: Washington, DC | H17: Mays Landing, NJ | I17: 1 to 50 employees | J17: 1997 | K17: Company - Private | L17: Federal Agencies | M17: Government | N17: Unknown / Non-Applicable | O17: -1
A18: 16 | B18: Data Scientist - Contract | C18: $137K-$171K (Glassdoor est.) | D18: We are an ambitious, well-funded startup with plans to change a $1 trillion-dollar global industry. This is no ordinary startup. We have a proven management team that has done it before, done it before together, and done it before in the travel industry. The company is overflowing with fiercely intelligent people who have tons of energy and an upbeat view of the future. We all act like owners and we get a huge kick out doing great work and doing it fast. We like it even more when we come up with a fresh way to solve a problem. Above all, we are devoted to solving customer problems, because thatвЂ™s at the center of everything we do. ABOUT YOU YouвЂ™re an experienced data scientist with skills honed on internet commerce scale information and comfortable contributing to and improving a production system. YouвЂ™re comfortable operating within an agile environment working with cross discipline teams YouвЂ™re excited about working in a python production and DS stack and have defendable positions on which tools you choose. YouвЂ™ve got proven experience with some combination of scikit-learn, TensorFlow, and PyTorch and have delivered scalable decision systems as part of a team You believe ML can be a powerful tool when combined with human in the loop domain experts YouвЂ™re Intrigued by the challenge of what a machine based travel agent could look like WeвЂ™d like to see demonstrated knowledge in one or more of the following areas Delivering recommendation systems with direct experience tuning models for personalization at consumer internet scale Implementation and continuous improvement of a pricing system. Background in pricing theory and building market driven pricing system highly desired Experience with modeling and implementing a loyalty program Building production level computer vision APIs ABOUT THE GIG You will be focussing on building new machine learning services to meet the needs of our internal and external customers We put the customer first - our goal is to reduce their cognitive load, provide transparent and actionable recommendations and improve the business trip with data and machines. All work youвЂ™ll do is in direct support of that data science mission. YouвЂ™ll listen directly to customers, identify opportunities and form hypotheses. Build prototypes and test them in production. Iteration and measurement are essential parts of what we do. Be integral part of a cross-discipline team including product, engineering and UX thatвЂ™s looking to redefine the travel shopping experience from a data-centric point of view. Refine and improve a decision system that powers our unit economics. Understand and simulate impact of changes to company wide KPIs. Help build a data powered narrative that we can repeatedly deliver to our customer at scale and with high fidelity. Refine and improve our systems that mine large scale travel marketplace data, our consumer purchase behavior and the traveler experience timeline. ABOUT US We are positive, passionate, playful, and always pushing to be better. Our team is a hodgepodge of challenge seekers, travel gurus, startup junkies, and data-miners who see the big picture. YOU WANT TO TALK TO US IFвЂ¦ В· You are motivated by disrupting the norm. В· You have a great sense of humor and take your profession seriously, but not yourself. В· Your entrepreneurial spirit drives your bias for action. В· You are all about constructive feedback - you can dish it out and you can take it. В· You thrive in the frenetic energy of a startup. Upside Travel is an equal opportunity employer and encourages people of all backgrounds, genders, ethnicities, abilities, and sexual orientations to apply. We are committed to being an inclusive place to work, while maintaining a workforce that represents the communities we serve. | E18: 4.1 | F18: Upside Business Travel 4.1 | G18: Remote | H18: Washington, DC | I18: 51 to 200 employees | J18: 2015 | K18: Company - Private | L18: Internet | M18: Information Technology | N18: Unknown / Non-Applicable | O18: -1
A19: 17 | B19: Data Scientist | C19: $137K-$171K (Glassdoor est.) | D19: Job Success Profile Data Scientist Buckman is a privately held, global specialty chemical company with headquarters in Memphis, TN, USA, committed to safeguarding the environment, maintaining safety in the workplace, and promoting sustainable development. Buckman delivers exceptional service and innovative solutions to our customers globally in the pulp and paper, leather, and water treatment sectors to help boost productivity, reduce risk, improve product quality, and provide a measurable return on investment. Buckman is in the middle of a digital transformation of its businesses and focused on building the capabilities and tools in support of this. Position Summary Buckman is seeking an experienced Data Scientist to lead the development of a Data Science program at our Memphis facility. You will work closely with Buckman stakeholders to derive deep industry knowledge across paper, water, leather, and performance chemical industries. You will help develop a data strategy for the company including collection of the right data, creation of the data science project portfolio, partnering with external providers, and augmenting capabilities with additional internal hires. A large part of the job is communicating and developing relationship with key stakeholders and subject matter experts to tee up proofs of concept projects to demonstrate how data science can be used to solve old problems in unique and novel ways. You will not have a large internal team to rely on, at least initially, so individual expertise, breadth of data science knowledge, and ability to partner with external companies will be essential for success. In addition to the pure data science problems, you will be working closely with a multi-disciplinary team consisting of sensor scientists, software engineers, network engineers, mechanical/electrical engineers, and chemical engineers in the development, and deployment of IoT solutions. If you like working for an entrepreneurial company with a Sustainability mission and digital ambitions at the core of its strategy, Buckman is the place for you. Competencies Needed for Success BachelorвЂ™s degree in a quantitative field such as Data Science, Statistics, Applied Mathematics, Physics, Engineering, or Computer Science 5+ years of relevant working experience in an analytical role involving data extraction, analysis, and visualization and expertise in the following areas: Expertise in one or more programming languages R, Python, MATLAB, JMP, Minitab, Java, C++, Scala Key libraries such as Sklearn, XgBoost, GLMNet, Dplyr, ggplot, Rshiny Experience and knowledge of data mining algorithms including supervised and unsupervised machine learning techniques areas such as Gradient Boosting, Decision Trees, Multivariate Regressions, Logistic regressions, Neural Network, Random Forest, Support Vector Machine, Naive Bayes, Time Series, Optimization Microsoft IoT/data science toolkit: Azure Machine Learning, Datalake, Datalake analytics, Workbench, IoT Hub, Stream Analytics, CosmosDB, Time Series Insights, PowerBI Data querying languages (e.g. SQL, Hadoop/Hive) and Preferred Qualifications A demonstrated record of success with a verifiable portfolio of problems tackled Preferred Qualifications MasterвЂ™s or PhD degree in a quantitative field such as Data Science, Statistics, Applied Mathematics, Physics, Engineering, or Computer Science Experience in the specialty chemicals sector or similar industry Background in engineering, especially Chemical Engineering Experience starting up a data science program Experience working with global stakeholders Experience working in a start-up environment, preferably in an IoT company Knowledge in quantitative modeling tools and statistical analysis Preferred Work Style A strong business focus, ownership and inner self-drive to data science solutions to real-world customers with tangible impact. Ability to collaborate effectively with multi-disciplinary and passionate team members. Ability to communicate with a diverse set of stakeholders Strong planning and organization skills, with the ability to manage multiple complex projects A life-long learner who constantly updates skills Language: English Location: Remote Work Opportunity - Flexible Travel: <10> | E19: 3.5 | F19: Buckman 3.5 | G19: Memphis, TN | H19: Memphis, TN | I19: 1001 to 5000 employees | J19: 1945 | K19: Company - Private | L19: Chemical Manufacturing | M19: Manufacturing | N19: $500 million to $1 billion (USD) | O19: -1
A20: 18 | B20: Data Analyst II | C20: $137K-$171K (Glassdoor est.) | D20: The Data Analyst II is responsible for data entry and maintenance for our integrated enterprise system (SAP). As part of the Data Integrity team, this position is responsible for the accurate entry of data into SAP. The Data Integrity team is responsible for the efficient and effective management of part master data. This will require an individual with exceptional attention to detail, intermediate to advanced computer skills, in-depth knowledge of our business, products and processes. WORK PERFORMED To perform this job successfully, an individual must be able to perform each essential duty satisfactorily. The requirements listed below are representative of the knowledge, skill, and/or ability required. Essential Functions of the Job: Product Data вЂ“ Responsible for managing product information levels to established standards Maintain data to meet company standards Data includes images, technical specifications and other data elements Ensure automated data feeds successfully populate materials Manually populate non-automated data as necessary via proprietary system Identify system enhancements to improve automated processes and quality of information Perform audits to ensure accuracy of assigned manufacturers or categories Communicate with providers and manufacturers to ensure complete product data is supplied Request necessary information Identify areas of improvement and provide feedback Review data standards for assigned manufacturers and/or categories Implement data standard improvements through manual and automated means to meet needs Provide customer service support for both external and internal customers Support and validate teammate adherence to master data policies. Material Maintenance вЂ“ Responsible for maintaining product catalog to established standards; Performing Price File Maintenance Review automated data feeds for successful materials creation Ensure materials are created correctly via download process Identify and communicate reasons for automated failures to improve process Manually process download failures Determine if Sales requests meet Insight Catalog Policy Review opportunities and determine if it is appropriate business for Insight Provide guidance to address future opportunities Ensure materials are not added to the catalog that do not fit Insight strategy Manually create non-automated materials proactively or reactively according to company policy Create materials via proprietary systems and/or SAP Determine appropriate source, costing and categorization Process internal requests for creation Discontinue materials that are no longer available and/or based on company policy Other projects вЂ“ Responsible for completing additional projects and assignments as required by the department All other assigned duties MINIMUM REQUIREMENTS Education and/or Experience: Associates degree or above from a college or university; or 3 years industry work experience. KNOWLEDGE, SKILLS, AND ABILITIES Following are the skills, knowledge and abilities necessary to perform this job Advanced spreadsheet skills Ability to analyze and troubleshoot information for resolution Ability to work well in cross-functional teams Ability to multi-task in a fast-paced environment Ability to meet aggressive service-level agreements Ability to take a complex process or technology and create easy-to-follow copy Excellent written and verbal communication, with strong editing skills Knowledge of AP style Vast knowledge of technical writing and styles associated with it Collaborating with marketing and IT on search engine relevancy as it relates to parts dataвЂ™s influence Proficiency with MS Word, Excel, Outlook and SAP. Ability to write reports and/or business correspondence. Ability to effectively present information and respond to questions from groups of managers, customers, other employees. Ability to effectively present information to other departments and manufacturer representatives. Ability to read, analyze, and interpret business documents. Ability to effectively communicate via email, phone and in person. Ability to understand processes and identify areas of improvement. Ability to multi-task and demonstrate strong organizational details. | E20: 4.2 | F20: Insight Enterprises, Inc. 4.2 | G20: Plano, TX | H20: Tempe, AZ | I20: 5001 to 10000 employees | J20: 1988 | K20: Company - Public | L20: Enterprise Software & Network Solutions | M20: Information Technology | N20: $5 to $10 billion (USD) | O20: CDW, PCM, SHI International
A21: 19 | B21: Medical Lab Scientist | C21: $137K-$171K (Glassdoor est.) | D21: Responsibilities The Medical Laboratory Scientist is responsible for obtaining or receiving specimens, performing clinical laboratory tests by standardized procedures, understanding method principles, performing quality control, performing preventive maintenance, and interpreting results accurately, acceptably and within critical limits. The MLS works independently, organizing work to meet established deadlines and validates all data obtained. Qualifications Bachelor's Degree: Baccalaureate Degree in Medical Technology, Clinical Laboratory Science, Medical Laboratory Science or related science (Required) Minimum of 1 year of experience Certification and Licensure Requirements. MLS (ASCP) (Preferred) 3p-1130p 2-Evening | E21: 3.5 | F21: Tower Health 3.5 | G21: West Grove, PA | H21: Reading, PA | I21: 5001 to 10000 employees | J21: 2017 | K21: Nonprofit Organization | L21: Health Care Services & Hospitals | M21: Health Care | N21: Unknown / Non-Applicable | O21: -1
A22: 20 | B22: Data Scientist | C22: $137K-$171K (Glassdoor est.) | D22: Role Description As a data scientist at Triplebyte, youвЂ™ll have the opportunity to work on a variety of challenges to help us scale. You'll be part of a small team, who are leveraging data to fix technical hiring. Your day to day, will include a mix of dataset acquisition, statistical modeling, exploratory data analysis, and software engineering. YouвЂ™ll report directly to Triplebytes' Head of Machine Learning and will work alongside a team of 6-8 machine learning engineers and data scientists. Fields your work will touch on Psychometrics Recommender systems Time series analysis Survival analysis Bayesian inference Probabilistic programming This is an ideal role for a data scientist who wants the scope and responsibility to own features/products from the inception and research phase through to measuring real-world results. About Triplebyte Triplebyte is a hiring marketplace used by companies like Apple, Dropbox, Stripe, and Instacart to hire the best technical talent. We are on a mission to build a meritocratic hiring process, and we do all our evaluation background blind. Our ultimate goal is to collect the largest dataset and use this to build the world's best technical hiring process. No other company has successfully done what we're doing in this field. We are growing extremely quickly, working on a problem that is fundamental, sitting at the crossroads between the workforce and employers. Ten years from now, it'll look silly to use anything other than Triplebyte for technical hiring. Company Culture We have a laid-back, friendly office culture. Over lunch you'll often find us discussing the latest in technology, books, and pop culture, and then maybe getting in a quick game of chess or babyfoot (foosball). Since we're an early-stage company, we move fast, and it's important that each member of our team is able to take ownership of projects by defining problems, brainstorming solutions, and running experiments. | E22: 3.2 | F22: Triplebyte 3.2 | G22: New York, NY | H22: San Francisco, CA | I22: 51 to 200 employees | J22: 2015 | K22: Company - Private | L22: Computer Hardware & Software | M22: Information Technology | N22: Unknown / Non-Applicable | O22: -1
A23: 21 | B23: Data Scientist/Machine Learning | C23: $137K-$171K (Glassdoor est.) | D23: PulsePointв„ў, a global programmatic advertising platform with specialized healthcare expertise, fuses the science of programmatic targeting, distribution, and optimization with the art of brand engagement. The PulsePoint platform is powered by terabytes of impression-level data, allowing brands to efficiently engage the right audiences at scale while helping publishers increase yield through actionable insights. Our organization has a strong history of utilizing machine learning, contextualization, and targeting to distribute advertising to the right consumers at the right time and create real connections across the internet. We are now taking that knowledge and expertise to solve challenges within healthcare in order to create better health outcomes through Radical Health Personalizationв„ў. The goals of the PulsePoint Data Science team: Optimize and validate targeting mechanisms for specific health conditions; Improve and optimize our proprietary contextualization and recommendation engines that handle millions of transactions per second, trillions each month; Improve and optimize our buying platform to ensure cost efficiency and to deliver ad campaigns within budget, target and time constraints; Collaborate with internal Health experts to design and support rapid assessment, analysis, and prototyping of ideas for achievable commercialization. What you'll be working on: Improve existing or develop new traffic segmentation algorithms and estimations of bid landscapes within each segment; Optimize real-time bidding strategies to efficiently spend ad budgets delivering campaign targets given various constraints; Support and enhance the existing work on health user profiling, prediction, and targeting tools; Improve page contextualizer technology: work with healthcare topics detection algorithms, keywords/phrases extraction, general and aspect-based sentiment analysis; Contribute on projects relating to patient/physician identity for cross-device tracking, profiling and targeting; Support existing codebase for data integration and production support for our core models. What you need to be successful in this role: 3+ years of full-time experience working as a Statistician/ Machine Learning Engineer/ Data Scientist; Advanced knowledge of Big Data technologies such as Hadoop, Hive/Impala and Spark; Advanced knowledge of Python using the numpy/scipy/pandas/sklearn stack; Advanced knowledge of classical ML models (logistic regression, decision trees, boosting, bagging, SVM, Bayesian methods, etc) and at least basic knowledge in different Neural Network models (CNN, RNN, auto-encoders, transformers); Being confident user of Unix-like systems, Dockers, git, bash; MS/PhD in Applied Mathematics, Statistics, Machine Learning, Computer Science, Physics; or BS with several years of applied machine learning experience What we offer: Sane work hours Generous paid vacation/company holidays Vacation reimbursement, sabbatical, pawternity leave, marriage leave, honeymoon bonus Comprehensive healthcare with 100%-paid medical, vision, life & disability insurance $2,000 annual training and development budget Complimentary annual memberships to One Medical, NY Citi Bike and SF Ford GoBike Monthly chair massages Free fitness classes (spin, yoga, boxing) Gym reimbursement, local gym membership discounts Onsite flu shots, dental cleanings and vision exams Annual company retreat Paid parental leave and a lot of new parent perks Emergency childcare credits 401(k) Match and free access to a financial advisor Volunteer Time Off and Donation Matching, ongoing group volunteer opportunities Team lunches, Sip & Social Thursdays, Game Nights, Movie Nights Healthy snacks and drinks And there's a lot more! | E23: 4.3 | F23: PulsePoint 4.3 | G23: New York, NY | H23: New York, NY | I23: 51 to 200 employees | J23: 2011 | K23: Company - Private | L23: Internet | M23: Information Technology | N23: $100 to $500 million (USD) | O23: Crossix Solutions Inc., AppNexus, The Trade Desk
A24: 22 | B24: Human Factors Scientist | C24: $137K-$171K (Glassdoor est.) | D24: Human Factors Scientist ID 3336 Location Phoenix, AZ Practice/Center Human Factors Apply Now Exponent is a leading engineering and scientific consulting firm. Our multidisciplinary team of scientists, engineers, physicians, and regulatory consultants brings together more than 90 different disciplines to solve complicated problems facing corporations, insurers, government entities, associations and individuals. Our approximately 1000 staff members work in 26 offices across the United States and abroad. Exponent has over 800 consultants, including more than 500 that have earned a doctorate in their chosen field of specialization. Exponent's Human Factors Practice is seeking a Scientist for our Phoenix, AZ office. This position will be responsible for analyzing human performance related to a wide variety of real world scenarios involving automobiles, occupational work and consumer products, and for serving as project manager on a potentially large number of such engagements. Additional responsibilities will include: Supporting a wide range of consulting activities that involve human factors in accidents and their prevention, including limitations of human perceptual, cognitive, and response capabilities Developing client contacts and helping to grow future business opportunities Working on multi-disciplinary projects spread across the nation Providing case management, data processing, and analytical project support Conducting research to obtain and review technical data, scientific literature, and standards Participating in the design and evaluation of warnings, consumer products, and safety information The ideal candidate for this position has a strong interest in applying their training to human performance questions involving operator behavior, occupational safety, consumer-product interaction, and environment navigation, and also possesses a strong scientific background in the foundations of cognition, perception, and human decision-making. Candidates should furthermore be comfortable working in a collaborative and fast-paced professional engineering and scientific consulting environment, which demands a high degree of self-motivation, dedication, and resilience to stress. Qualifications for this position include: Ph.D. in Experimental or Cognitive Psychology/Neuroscience Excellent written and verbal communication skills as well as strong interpersonal skills Strong mathematical aptitude and proficiency with statistics Solid foundation in science of cognition, perception, and human decision making Consummate project management skills and ability to juggle multiple teams concurrently with an eye for detail Must be assertive, a self-starter, and able to work with accuracy under pressure and/or To learn more about life at Exponent, check out our Graduate Students page at www.exponent.com/careers/grad-students! We are an Affirmative Action, Equal Employment Opportunity, Veterans and Disabled Employer. | E24: 3.5 | F24: Exponent 3.5 | G24: Phoenix, AZ | H24: Menlo Park, CA | I24: 1001 to 5000 employees | J24: 1967 | K24: Company - Public | L24: Consulting | M24: Business Services | N24: $100 to $500 million (USD) | O24: -1
A25: 23 | B25: Business Intelligence Analyst I- Data Insights | C25: $137K-$171K (Glassdoor est.) | D25: Position Summary Individuals within the Business Intelligence (BI) Analyst I role provide business intelligence, reporting, and data analysis needs for Customer Service and Delivery. They work closely with BI Consultants, end users, and IT teams to turn data into critical information and knowledge that can be used to make sound business decisions. It is essential that BI Analysts build an understanding of the CSD organization at a level of detail that enables them to identify and address critical issues. They provide data that is accurate, congruent and reliable, and ensure the information is easily available to users for direct consumption or integration with other systems. BI Analysts educate and train business partners and clients to use the data as an analytical tool, displaying the information in new forms and content for analysis and option exploration. BI Analysts work with users to determine business requirements, priorities, define key performance indicators (KPI), and develop BI and data warehouse (DW) strategy. They conduct analyses of functional business processes and functional business requirements and participate in the development of business cases in the support of process changes. This includes working with business and development teams to design, and document dashboards, alerts, and reports. This individual is accountable for providing leadership and independent initiatives in facilitating information gathering, structured documentation and presentation of findings to all levels of management. BI Analysts understand how data is turned into information and knowledge and how that knowledge supports and enables key business processes. They must have understanding of the business environment and an interest in going beyond the obvious, delving into the source, the definition, philosophy, and foundational roots of a data element to create information. They must work well within a team environment. Candidate Responsibilities Provides design support for the development of business intelligence solutions. Works on small to mid-sized and cross-functional IT and business intelligence solutions. Works on multiple tasks/projects as team member. Participates in workstream planning process including inception, technical design, development, testing and delivery of BI solutions. May participate in project management estimation process. Works with internal and external customers and IT partners to develop and analyze business intelligence needs. Provides input to business requirements for the design of solutions. Interprets business requirements and determines optimum BI solutions to meet needs. Identifies and provides input to new technology opportunities that will have an impact on the Enterprise wide BI systems. Designs Institute-wide views and custom reports. May perform analysis for a wide range of requests using data in different formats and from various platforms. Researches business problems and creates models that help analyze these business problems. Provides input to the development of information quality metrics. Researches tools, frameworks and mechanisms for data analytics. Adheres to current standards. Provides input to standards, policies and procedures for the form, structure, and attributes of the BI tools and systems. Designs and delivers end-user training and training materials. Trains users to transform data into action-oriented information and to use correctly. Functional Skills General knowledge of supported business functions, systems, and transactions Familiar with technology system processes, reporting functions, and methodologies Works effectively with associates from across the CGM Profit Center and with business and IT partners | E25: 3.5 | F25: Guardian Life 3.5 | G25: Appleton, WI | H25: New York, NY | I25: 5001 to 10000 employees | J25: 1860 | K25: Company - Private | L25: Insurance Carriers | M25: Insurance | N25: $5 to $10 billion (USD) | O25: Northwestern Mutual
A26: 24 | B26: Data Scientist | C26: $137K-$171K (Glassdoor est.) | D26: WhatвЂ™s significantly better than working on a typical data science team? How about working on a data science team in which youвЂ™re directly making an impact in the revolutionary field of artificial intelligence even as an entry level team member? (well, statistically significant that is). Pardon the pun, but at Spectrum weвЂ™re certain that our team is pumped up to work not only with like-minded data-savvy and fun loving professionals, but also to work with cutting edge new tools like our predictive, artificially intelligent proprietary software. So, if your confident that you want to make a direct impact in your next job today, then please keep on reading. Responsibilities Beyond working with state of the art technology you will have many different fantastic projects to work on as a Data Scientist at Spectrum. Here are just a few different responsibilities you can expect off the bat: Work with IT teams, management and/or data scientists to determine organizational goals Mine data from primary and secondary sources Clean and prune data to discard irrelevant information Analyze and interpret results using standard statistical tools and techniques Pinpoint trends, correlations and patterns in complicated data sets Identify new opportunities for process improvement Provide concise data reports and clear data visualizations for management Some Characteristics That Define You We understand that as a Data Scientist for Spectrum, you have many different professional goals and personal interests. As such here are just a few different things that typically define our team members on the Data Science team: Analytical. In order to solve problems and build innovative new digital marketing campaigns, it is essential that you know how to take an idea and analyze it from all of its angles. Patient. As a data scientist, you know that you work with extremely large data sets on a daily basis. As such we are looking for someone who is not only meticulous, but patient enough to sit and sift through that data in a thorough way. Creative. Beyond just analyzing data sets, you are an explorer and a puzzle solver. Pulling insights out of your data and understanding how those insights can better shape our tools is something that you live to do. Student. More so than most industries, the field of data science is always changing and evolving. As such, you are always looking to learn new things and gain new skills. Business-Savvy. Beyond the wicked data science skills you bring to the table, we also want you to consider the business implications of our data tools. From the ways our team will use them to how our customers will use them, we always want you to keep the user and the business application in mind. Required Skills and Experience On top of the many intangible skills you bring to the table, there are many skills that can help improve the efficiency and success of your work at Spectrum. Here are a few of those required skills and experience that you will come in with as a Data Scientist on our team: A bachelorвЂ™s degree/pursuing a bachelor's degree in computer science, mathematics, statistics, information systems, or a related field Experience with statistical modeling Fundamental knowledge of R and/or SAS languages Experience with SQL databases and database querying languages Experience with data mining and data cleaning Experience with data visualization and reporting techniques Written and verbal expression Benefits As a Data Scientist at Spectrum there are a ton of fantastic perks and benefits that come along with your work. Here are just a few of the benefits you can expect when joining the Spectrum family: Comprehensive medical & dental insurance Retirement planning & company matching Generous PTO, including sick days & holidays A state-of-the-art office environment Nintendo Switch in-office gaming such as FIFA, Arms, Mario Kart, and Rocket League Year-round gym memberships Paid continuing education Casual dress code Flexible scheduling Free-Lunch-Friday Company sponsored parties and group activities outside of the office | E26: 3.4 | F26: Spectrum Communications and Consulting 3.4 | G26: Chicago, IL | H26: Chicago, IL | I26: 51 to 200 employees | J26: 1992 | K26: Company - Private | L26: Advertising & Marketing | M26: Business Services | N26: $10 to $25 million (USD) | O26: -1
A27: 25 | B27: Data Scientist | C27: $137K-$171K (Glassdoor est.) | D27: Job Description Oversight is a leading provider of cloud-based artificial intelligence solutions automating and analyzing financial payment transactions to identify fraud, non-compliant purchases, and wasteful spending. Oversight analyzes over $2 trillion in expenditures annually at Fortune 5000 companies and government agencies worldwide. In this position as a Data Scientist, you will be working with a team of skilled and motivated data scientists and machine learning engineers designing and building AI solutions to expand our product line. Responsibilities Our team is at the fore front of building, operating and supporting business systems with machine learning at their core. As a Data Scientist you will be incorporating machine learning into our products in order to transform how companies find and manage spend risk throughout their organization. You will collaborate with cross functional teams on complex data science problems and be responsible for solution design, data preparation, model building, and model management. Ultimately, weвЂ™re looking for people who are excited by machine learning, data and technology, love to solve problems, constantly challenge themselves to provide the best user experience, can work well alone, have a wide range of skills and are able and willing to constantly learn. Skills Technical Skills/Requirements 3+ years real world experience in a data science or equivalent role Extensive experience designing and maintaining a machine Learning pipeline вЂ“ ETL, feature engineering, modeling, predicting, explaining, deploying and ongoing diagnostics Excellent pattern recognition and predictive modeling skills Experience communicating complex models and designing Strong experience with data processing and data analytics Experience analyzing a wide variety of structured and unstructured data Strong communication and data presentation skills Experience in both R&D and commercial software product development environment is a plus Technologies Expertise in python, scikit-learn, and pandas Experience with Deep learning frameworks (FastAI , Keras, PyTorch etc.) preferred SQL Linux Interested and qualified candidates should submit a resume with salary requirements to recruiter@oversightsystems.com. About Oversight The worldвЂ™s largest companies and government agencies trust Oversight to identify enterprise spend risk no matter where it resides in their organization. OversightвЂ™s AI-powered platform drives financial transformation by reducing audit effort and eliminating data silos to monitor and analyze 100% of spend transactions with unparalleled accuracy. With full visibility into spend, Oversight customers find and prioritize employee-initiated and third-party spend risk that would otherwise go undetected by in-house processes. By identifying process breakdowns and making corrections early, Oversight helps optimize budgets, reduce out-of-policy spending by 70% while maximizing audit efficiency and eliminating cash leakage. Oversight is an equal opportunity employer. Job Applicant Privacy Notice | E27: 4.7 | F27: Oversight Systems 4.7 | G27: Atlanta, GA | H27: Atlanta, GA | I27: 51 to 200 employees | J27: 2003 | K27: Company - Private | L27: Computer Hardware & Software | M27: Information Technology | N27: $25 to $50 million (USD) | O27: -1
A28: 26 | B28: Data Scientist - Risk | C28: $137K-$171K (Glassdoor est.) | D28: Job Title: Data Scientist (Risk) Location: Orlando, Florida Manager: Head of Data Science About LSQ LSQ is a technology-driven provider of accounts receivable financing to companies who need working capital but may not be able to obtain sufficient financing from their bank. Our focus is to help businesses release the liquidity tied up in their accounts receivable. With financing from LSQ, a business can purchase more inventory, fill more orders, and take advantage of new growth opportunities. Our technology and data driven approach to providing working capital, along with our accounts receivable management services, allows our clients to driving business success. Job Overview LSQ is searching for a Data Scientist (Risk) to join our growing team of analytics experts. The hire will be responsible for building data driven tools to automate and scale risk decisions decision points include, fraud detection, commercial credit analysis, and invoice payment behavior. The ideal candidate is an experienced researcher and data wrangler who enjoys applying complex theories to solve real world business problems. The Data Scientist will need to collaborate effectively with both technical (engineers, data experts) and non-technical (business users) colleagues to bring the data to life. Responsibilities of Data Scientist (Risk) We have 20+ years of real-world commercial data weve observed businesses and their interactions with other businesses across market cycles, industries, and catastrophic events. Build risk tools that optimize for velocity and scale. Build risk tools that optimize science & art you will work with risk experts who have been in the trenches (and learned from losses). Augment human decisions with machine. Lay the foundation for scale. A data science framework for optimal data acquisition, model training and deployment. Dont take short-cuts. Bring quantitative and statistical rigor to your body of work. Lead by example. You are joining a data team at ground-level. Building and inserting a data team, into a 20+ year old company (organism) will be hard, but rewarding. Qualifications for Risk Data Scientist Curiosity, Grit, and Humility 5+ years of experience of hands-on data science role Previous experience of building commercial finance risk tools should be beneficial, but not required Bachelor or Masters degree in Data Science, Operations Research, Computer Science, Industrial Engineering, Statistics, or another quantitative field A toolkit of modern data science techniques Experience with any data science tools/packages: Python, R, SAS, XGBoost, TensorFlow, NLTK Experience with any big data tools: Hadoop, Spark, Kafka, Data Bricks Experience with any reporting tools: Tableau Server, Power BI, SSRS, Excel Experience with any AWS cloud services: EC2, EMR, RDS, Redshift, Aurora, S3 Experience with any Stream-processing systems: Storm, Spark-Streaming Position Type and Expected Hours of Work: This is a full-time position. Days and hours of work are Monday through Friday, 8:00 a.m. to 5 p.m. Occasional evening and weekend work may be required as job duties demand. Physical Demands: While performing the duties of this job, the employee is regularly required to sit and use hands to finger, handle, or feel. The employee is frequently required to reach with hands and arms and talk or hear. The employee is occasionally required to stand; walk and stoop, kneel, crouch. Travel: There will be minimal travel required for this position. LSQ is an Equal Opportunity Employer that does not discriminate on the basis of actual or perceived, race, religion, color, sex (including pregnancy and gender identity), sexual orientation, parental status, national origin, age, disability, family medical history or genetic information, political affiliation, military service, any other non-merit based factor or any other characteristic protected by applicable federal, state or local laws. Our leadership team is dedicated to this policy with respect to recruitment, hiring, placement, promotion, transfer, training, compensation, benefits, employee activities and general treatment during employment. If youd like more information about your EEO rights as an applicant under the law, please click here http://www1.eeoc.gov/employers/poster.cfm | E28: 4.2 | F28: LSQ 4.2 | G28: Orlando, FL | H28: Orlando, FL | I28: 51 to 200 employees | J28: 1996 | K28: Company - Private | L28: Investment Banking & Asset Management | M28: Finance | N28: $100 to $500 million (USD) | O28: -1
A29: 27 | B29: Data Scientist-Human Resources | C29: $137K-$171K (Glassdoor est.) | D29: Lexington, MA, US #job-location.job-location-inline { display: inline; } Company: MIT Lincoln Laboratory Job Summary Responsible for the collection, synthesis, and analysis of employee data to meet organizational objectives. Gains insight into key Human Resources related business opportunities and deliverables by applying statistical analysis techniques to examine structured and unstructured data from multiple disparate sources. Interprets results from multiple sources using a variety of techniques, ranging from simple data aggregation via statistical analysis to complex data mining. Uses advanced mathematical, statistical, querying, and reporting methods to develop solutions. Develops information tools, algorithms, dashboards, and queries to monitor and improve business performance. Successful candidates will have demonstrated: Strong interpersonal, team building, communication and presentation skills to effectively communicate and collaborate with all levels of the organization. An ability to maintain strict confidentiality as well as business and professional ethics. Strong organizational skills, attention to detail and ability to handle multiple tasks. Flexibility and ability to work effectively and meet deadlines in a dynamic, fast-paced environment. Ability to perform successfully in a data driven, service-oriented environment and to interpret rules and guidelines flexibly to enhance the business values and the diverse culture. Requirements BS required, MS preferred in related disciplines such as Computer Science, Statistics, and/or Mathematics with 5-8 years of relevant experience. Experience working with sensitive data, predictive analytics and behavioral science based information preferred. Must have demonstrated experience with some or all of the following: Data and Quantitative Analysis / Decision Analytics / Predictive Modeling / Data-Driven Personalization / KPI Dashboards and BPI Plans / Big Data Queries and Interpretation / Data Mining and Visualization Tools / Machine Learning Algorithms / Business Intelligence (BI) / Research, Reports and Forecasts. In addition, must have experience with some or all of the following: Data and Computer Science proficiency: SPSS, SAS, R, Rstats, Python, Apache Spark, Microsoft PowerBI, Matlab, HIVE, Pig, data warehouse (DW, DWH), Hadoop, Google Analytics, data mart projects, data management, machine learning, predictive analytics, prescriptive analytics, streaming analytics, SQL, Business Objects (Crystal Reports, Dashboards, WEBI), SAP BW, SAP HANA, SAP Lumera, and many and/or other products is a plus. For Benefits Information, click http://hrweb.mit.edu/benefits Selected candidate will be subject to a pre-employment background investigation and must be able to obtain and maintain a Secret level DoD security clearance. MIT Lincoln Laboratory is an Equal Employment Opportunity (EEO) employer. All qualified applicants will receive consideration for employment and will not be discriminated against on the basis of race, color, religion, sex, sexual orientation, gender identity, national origin, age, veteran status, disability status, or genetic information; U.S. citizenship is required. Requisition ID: 28943 Nearest Major Market: Boston Job Segment: Database, Scientific, Scientist, ERP, Developer, Engineering, Technology, Science | E29: 3.8 | F29: MIT Lincoln Laboratory 3.8 | G29: Lexington, MA | H29: Lexington, MA | I29: 1001 to 5000 employees | J29: 1951 | K29: Nonprofit Organization | L29: Aerospace & Defense | M29: Aerospace & Defense | N29: Unknown / Non-Applicable | O29: -1
A30: 28 | B30: Data Scientist | C30: $137K-$171K (Glassdoor est.) | D30: Kingfisher Systems, Inc. specializes in providing a full range of Information Technology, Cybersecurity, Intelligence, and support services to the U.S. Government. Kingfisher Systems core competency is technology-enabled services, with a specific focus on national security. Since 2005, Kingfisher has established itself as a recognized and trusted mission partner whose mission is safeguarding sensitive information, operations, and programs for our Federal customers and warfighters. Responsibilities: Kingfisher Systems, Inc. is seeking a Data Scientist to implement effective and innovative solutions meshing disparate data types to discover insights and trends in human capital information. Perform work on a data science team to advance HCA across the IC. Centralize IC data collection and synthesis, including survey data, enabling strategic and predictive analytics to guide business decisions. Develop or utilize complex programmatic and quantitative methods to find patterns and relationships in data sets; lead statistical modeling, or other data-driven problem-solving analysis to address novel or abstract business operation questions; and incorporate insights and findings into a range of products. Create detailed write-ups of processes used, logic applied, and methodologies used for creation, validation, analysis, and visualizations. Write ups shall occur initially, within a week of when process is created, and updated in writing when changes occur. Adapt freeware solutions such as R, and modular solutions for maximum flexibility. Provide an advanced capability for data analysis of human capital information from disparate data types, promoting visualization and storytelling to discover insights that help guide business decisions. Be forward leaning, exploring HCA solutions that benefit IC elements individually and collectively. Let the data tell the story including what is inconsistent or contradictory and automate data cleansing. Integrate data solutions and collection with IC Information Technology Enterprise to enhance connectivity with Identify and customize, if necessary, Commercial Off The Shelf (COTS) Information Technology (IT) tools for administration and data collection, or to leverage, support, and integrate the process with tools built for the IC and/or its component elements. Any tools developed shall be web-based and web-enabled, designed to maximize feedback effectiveness while protecting employee assessment information, and include both structured interview and web-based tools for gathering feedback. Assist in the development and maintenance of financial procedural guidance, templates and data formats, for identifying IC-wide workforce numbers, to include government, military, and contractor support. Review, assess data, identify data deficiencies and recommend solutions for remediation. Support quantitative and analytic efforts for workforce planning, development of financial procedural guidance data formats related to the Congressional Budget Justification Book (CBJB) planning displays, and analytic support for budget management and planning. Assist with ad hoc data requests from Congress, IC elements or as required by the client. Coordinate and facilitate community of practice and working group meetings, to include meeting logistics, agenda development and presenter coordination, day-of execution and facilitation, documentation and distribution of meeting minutes and presentations. Present or coordinate presentations on relevant topics as directed by the client. Required Skills: Data analysis and modeling on an independent (i.e., without significant guidance or direction) basis. Demonstrated experience in developing and applying quantitative methods to find patterns and relationships in large human capital data sets (such as the Human Capital Data Call, Foreign Language Data Call, FAIR act data, etc.) using statistical and graphical packages. Applied knowledge in the mathematical sciences such as probability, statistics, predictive modeling, computational social sciences; computer programming such as but not limited to Python, R, SAS, SPSS; and COTS data visualization packages such as but not limited to Tableau. Experience with Oracle Database and Procedural language/Structured Query Language (PUSQL). Preferred Experience: C#.NET, ASP.NET Model View Controller (MVC), jQuery, and Cascading Style Sheets (CSS), etc. Structuring data, natural language processing, database technologies, and machine learning algorithms. Ability to translate complex, technical, or analytic findings into an easily understood narrative- tell a story with the data in graphical, verbal, or written form. Demonstrated professional experience in developing quantitative financial analysis related to budget formulation and execution. Experience in development of financial procedural guidance data formats related to CBJB workforce displays and analytic support, resource management and planning. Demonstrated experience in human resource management supporting the federal government. Demonstrated experience in the use of programming, design, development, and implementation of on-line and automated survey instruments. Years of Experience: 10 years of relevant experience in a related field (International Relations, computer science, mathematics, statistics, political science etc.). Degree Requirement: Bachelor's or advanced degree in social sciences or related fields Related fields may include statistics, mathematics, computer science, physical science, economics, or engineering. Minimum Clearance Requirement: Minimum Top Secret clearance with SCI Eligibility. Applicants selected will be subject to an additional security investigation and thus may have additional eligibility requirements to meet. Kingfisher Systems, Inc. is an Equal Opportunity Employer. All qualified applicants will receive consideration for employment without regard to race, color, religion, sex, national origin, age, protected veteran status, among other things, or status as a qualified individual with a disability. | E30: 4.5 | F30: Kingfisher Systems 4.5 | G30: McLean, VA | H30: Falls Church, VA | I30: 51 to 200 employees | J30: 2005 | K30: Company - Private | L30: Federal Agencies | M30: Government | N30: $25 to $50 million (USD) | O30: -1
A31: 29 | B31: Data Scientist | C31: $137K-$171K (Glassdoor est.) | D31: Formation provides personalization for the largest enterprise businesses in the world. We work with high volume data streams to deliver tailored experiences and orchestrate physical and digital exchanges into a seamless journey. Our Data Science Team is transforming the way people engage across multiple industries. You'll collaborate closely with engineers and share responsibility throughout the product life-cycle. You'll work in small, self-sufficient teams with a common goal: deliver excellent data science solutions anchored in a culture of quality, delivery, and innovation. As a Data Scientist at Formation you're capable of working in an agile data science environment to generate and test hypotheses quickly. You're also passionate about improving, optimizing, and developing new reinforcement learning (RL) strategies to enhance the value of our platform. Key Responsibilities: Apply RL and statistical analysis to complex, real-world problems through massive data sets Independently design, test, and productionize RL-based experimentation to refine customer strategies Collaborate with colleagues in product and customer success roles, sharing responsibility throughout the product life-cycle Ability to explore an unfamiliar and large data sets with big data tools such as Hive or Spark Present methodology and results to external stakeholders and Fortune 500 clients Skills and Experience: Minimum 2 years experience as a Data Scientist, prior software development experience is a plus Master's or Ph.D. in a relevant technical field (e.g. Computer Science, Mathematics, Statistics, Physics) Prior experience with RL frameworks such as TensorFlow or Vowpal Wabbit, and Spark is a plus Machine learning knowledge with a focus on contextual bandits, reinforcement learning, recommender systems, knowledge of common Data Science concepts related to e-commerce (e.g. lifetime value, net incremental revenue, churn) is a plus Demonstrated ability to communicate and collaborate with peers Demonstrated skills in result-driven problem solving About Formation Formation is the global leader in developing scalable solutions for individualized offers. We drive business results by building and deepening the relationship between big brands and their customers. We use artificial intelligence (AI) and machine learning (ML) algorithms to constantly analyze an audience and fine-tune offers. Our approach enables offers to become smarter and more effective with each customer interaction, resulting in a better experience. Formation strongly believes differing perspectives + passionate discourse achieve the greatest outcomes. We give our whole selves and we are building a team we can learn from. We are committed to inclusion and diversity and we are an equal opportunity employer. All applicants will receive consideration without regard to race, color, religion, gender, gender identity, sexual orientation, national origin, disability, or veteran status. Also, we are thrilled to be named one of the Top 50 startups by LinkedIn! Every member of our team makes Formation a special place to work and grow. Come join us and see for yourself! | E31: 2.8 | F31: Formation 2.8 | G31: San Francisco, CA | H31: San Francisco, CA | I31: 51 to 200 employees | J31: 2015 | K31: Company - Private | L31: Enterprise Software & Network Solutions | M31: Information Technology | N31: Unknown / Non-Applicable | O31: -1
A32: 30 | B32: Data Scientist | C32: $75K-$131K (Glassdoor est.) | D32: Overview Analysis Group is one of the largest international economics consulting firms, with more than 1,000 professionals across 14 offices in North America, Europe, and Asia. Since 1981, we have provided expertise in economics, finance, health care analytics, and strategy to top law firms, Fortune Global 500 companies, and government agencies worldwide. Our internal experts, together with our network of affiliated experts from academia, industry, and government, offer our clients exceptional breadth and depth of expertise. We are currently seeking a Data Scientist to join our team. The ideal candidate should be passionate about working on cutting edge research and analytical services for Fortune 500 companies, global pharma/biotech firms and leaders in industries such as finance, energy and life sciences. The Data Scientist will be a contributing member to client engagements and have the opportunity to work with our network of world-class experts and thought leaders. Job Functions and Responsibilities The candidate Data Scientist will help develop, maintain and teach new tools and methodologies related to data science and high performance computing. This position will also help Analysis Group in maintaining our leadership position in terms of advancing methodology and data analytics. The Data Scientist will be responsible for staying abreast of new developments in technology relating to data science, to share more broadly with Analysis Group. Key responsibilities for this position will include: Working with project teams to address data science/computing challenges Identifying opportunities for technology to enhance service offerings Acting as a resource and participating in client engagements and research as part of the project team Maintaining up-to-date knowledge of computing tools, providing technical training and helping to grow the in-house knowledge base, specifically in a Linux environment Presenting research at selected conferences Examples of activities for the Data Scientist will include: Developing data engineering and machine learning production systems for full stack data science projects Using natural language processing methodologies to work with EMR data, social media data and other unstructured data Optimizing procedures for managing and accessing large databases (e.g., insurance claims, electronic health records, financial transactions) Creating interactive analytics portals and data visualizations (e.g., using R/Shiny, Python/Flask, D3) Building and maintaining high performance computing (HPC) tools on grid and cloud computing environments Developing and reviewing software and packages in R, Python and other Object Oriented Languages Establishing optimized procedures for repetitive or computationally intensive tasks (C, C++, Cuda-C) Qualifications Strong credentials and experience in database management and data visualization Significant experience working within a Linux environment required Background in Statistics/Econometrics or Biostatistics Ideally PhD in Computer Science, Mathematics, Statistics, Economics or other relevant scientific degree with relevant experience. Other candidates with at least one year of experience in the field may also be considered Excellent written and verbal communication skills Project experience with R and/or Python Familiar with online/cloud computing/storage (e.g., AWS) Demonstrated experience working on project teams and collaborating with others SCIENTIFIQUE DES DONNГ‰ES *LвЂ™utilisation du genre masculin sert uniquement Г allГ©ger le texte et est utilisГ© ici en tant que genre neutre Survol Groupe dвЂ™analyse ltГ©e est lвЂ™une des plus grandes firmes de services-conseils en Г©conomie, comptant plus de 950 professionnels rГ©partis dans 14 bureaux en AmГ©rique du Nord, en Europe et en Asie. Depuis 1981, nous offrons notre expertise en matiГЁre de stratГ©gie, dвЂ™Г©conomie, de finance et dвЂ™analyse dans le domaine des soins de santГ© aux grands cabinets dвЂ™avocats, aux sociГ©tГ©s Fortune Global 500 et aux agences gouvernementales du monde entier. Nos professionnels en poste conjuguГ©s Г notre rГ©seau de spГ©cialistes affiliГ©s issus dвЂ™universitГ©s, dвЂ™industries spГ©cifiques et dвЂ™organismes gouvernementaux procurent Г notre clientГЁle un savoir-faire dвЂ™une portГ©e et dвЂ™une profondeur exceptionnelles. Nous sommes prГ©sentement Г la recherche d'un Scientifique des donnГ©es (В« Data Scientist В») pour se joindre Г notre Г©quipe. Le candidat idГ©al devrait ГЄtre passionnГ© par la recherche de pointe et les services analytiques pour les entreprises Fortune 500, les entreprises pharmaceutiques et biotechnologiques mondiales et les chefs de file dans des secteurs de la finance, l'Г©nergie et les sciences de la vie. Le Scientifique des donnГ©es sera un membre contributeur aux mandats des clients et aura l'occasion de travailler avec notre rГ©seau d'experts et de leaders d'opinion de classe mondiale. Description du poste et des responsabilitГ©s Le scientifique des donnГ©es aidera Г dГ©velopper, maintenir et enseigner de nouveaux outils et mГ©thodologies liГ©s Г la science des donnГ©es (В« Data Science В») et au HPC. Ce poste aidera Г©galement le Groupe d'analyse Г maintenir sa position de chef de file en ce qui a trait Г l'avancement de la mГ©thodologie et de l'analyse des donnГ©es. Le scientifique des donnГ©es sera chargГ© de se tenir au courant des nouveaux dГ©veloppements technologiques liГ©s Г la science des donnГ©es, afin de les partager plus largement avec le Groupe d'analyse. Les principales responsabilitГ©s de ce poste comprendront: - Collaborer avec les consultants pour relever les dГ©fis de la science des donnГ©es et de sciences informatiques - Agir Г titre de ressource et participer aux mandats et Г la recherche en tant que membre de l'Г©quipe de projet - Maintenir Г jour les connaissances sur les outils informatiques, fournir une formation technique et aider Г dГ©velopper la base de connaissances interne, notamment dans un environnement Linux - PrГ©senter la recherche Г des confГ©rences choisies Exemples de tГўches du scientifique des donnГ©es : - DГ©veloppement de systГЁmes de production en ingГ©nierie des donnГ©es ainsi quвЂ™en apprentissage machine pour des projets de science des donnГ©es full stack - Utiliser des mГ©thodologies NLP pour travailler avec les donnГ©es mГ©dicales Г©lectroniques, les donnГ©es des mГ©dias sociaux et d'autres donnГ©es non structures - Optimiser les procГ©dures de gestion et d'accГЁs aux grandes bases de donnГ©es (ex. rГ©clamations d'assurance, dossiers de santГ© Г©lectroniques, transactions financiГЁres) - CrГ©ation de portails d'analyse interactifs et de visualisations de donnГ©es (par exemple, en utilisant R/Shiny, Python/Flask, D3) - Construire et maintenir des outils de calcul de haute performance (HPC). - DГ©veloppement et rГ©vision de codes en R, Python et autres langages - Mise en place de procГ©dures optimisГ©es pour les tГўches rГ©pГ©titives ou intensives en calcul (C, C++, Cuda-C) Qualifications requises - Solides rГ©fГ©rences et expГ©rience dans la gestion de bases de donnГ©es et de la visualisation de donnГ©es - ExpГ©rience de travail significative dans un environnement Linux requise - ExpГ©rience antГ©rieure en statistique/Г©conomГ©trie ou bio-statistique - IdГ©alement, ГЄtre titulaire d'un doctorat en sciences informatiques, en mathГ©matiques, en statistique, en Г©conomie ou d'un autre diplГґme scientifique pertinent et possГ©der une expГ©rience pertinente. Les candidats ayant au moins un an d'expГ©rience dans le domaine peuvent Г©galement ГЄtre considГ©rГ©s. - Excellentes aptitudes de communication Г©crite et verbale - ExpГ©rience de projet avec R et/ou Python - FamiliaritГ© avec l'informatique en ligne/info nuagique et le stockage (AWS) - ExpГ©rience de travail dГ©montrГ©e au sein d'Г©quipes de projet et de collaboration avec d'autres personnes В­ Equal Opportunity Employer/Protected Veterans/Individuals with Disabilities. Please view Equal Employment Opportunity Posters provided by OFCCP here. The contractor will not discharge or in any other manner discriminate against employees or applicants because they have inquired about, discussed, or disclosed their own pay or the pay of another employee or applicant. However, employees who have access to the compensation information of other employees or applicants as a part of their essential job functions cannot disclose the pay of other employees or applicants to individuals who do not otherwise have access to compensation information, unless the disclosure is (a) in response to a formal complaint or charge, (b) in furtherance of an investigation, proceeding, hearing, or action, including an investigation conducted by the employer, or (c) consistent with the contractor's legal duty to furnish information. 41 CFR 60-1.35(c) | E32: 3.8 | F32: Analysis Group 3.8 | G32: Boston, MA | H32: Boston, MA | I32: 1001 to 5000 employees | J32: 1981 | K32: Private Practice / Firm | L32: Consulting | M32: Business Services | N32: $100 to $500 million (USD) | O32: -1
A33: 31 | B33: Data Scientist / Machine Learning Expert | C33: $75K-$131K (Glassdoor est.) | D33: Posting Title Data Scientist / Machine Learning Expert 04-Feb-2020 Job ID 288341BR Job Description ONE Global Discovery Chemistry Community working across 7 disease areas at the Novartis Institutes for BioMedical Research (NIBR) is seeking a highly talented and motivated Data Scientist to join our Global Discovery Chemistry Department in Cambridge, MA. The successful candidate will join an energizing and collaborative research organization, working alongside colleagues who are committed to improving human health through the discovery of transformative medicines. We are seeking a unique data scientist with the skills, experience and passion to extract new knowledge and disruptive insights from the large and rich body of data collected by one of the worldвЂ™s leading pharmaceutical companies. You will be a member of our global Computer-Aided Drug Discovery (CADD) group, an interdisciplinary team of expert molecular modelers, cheminformaticians, and data scientists. Teamed up with domain experts from biology, chemistry and translational medicine, this is a unique opportunity to develop and apply cutting-edge machine learning technologies to uncover insights to real-world drug discovery problems and innovate paths to new medicines. Your responsibilities include: вЂўDevelop and implement methods for extracting patterns and correlations from both internal and external data sources using machine learning toolkits вЂўDevelop workflows for conducting comparative analysis among NovartisвЂ™ diverse data sources as well as generalizing approaches developed in-house or externally. вЂўEnable open-source solutions for internal use and implement cutting-edge published scientific methods. вЂўDevelop customized machine learning solutions including data querying and knowledge extraction. вЂўInteract and be part of interdisciplinary project teams to drive effective decision-making by mining and developing predictive models вЂўDevelop new skills in the area of cheminformatics and drug discovery and leverage those to accelerate development of new machine learning algorithms вЂўKeep ahead of scientific literature and interact with internal and external scientists to integrate novel data science technologies Minimum requirements Education: Advanced degree (M.Sc. or higher) in data science and machine learning, statistics, computer sciences, cheminformatics, mathematics, computational chemistry, computational biology, bioinformatics, or related field. Minimum experience & skills: вЂўIn-depth experience with modern and classical machine learning methods вЂўStrong statistical foundation with broad knowledge of supervised and unsupervised techniques вЂўProgramming experience (preferred Python, R, C++) preferably in Linux and high-performance computing environments вЂўGood listener - strong, concise, and consistent written and oral communication вЂўTalent for communicating stories through data visualizations вЂўProven ability to collaborate with others вЂўA passion for tackling challenging problems and developing creative solutions вЂўA drive for self-development with a focus on scientific know-how Additional qualifications that will help in the role: вЂўDemonstrated impact using machine learning libraries, such as scikit-learn, PyTorch or similar in a cheminformatics context вЂўHands on experience with data analysis software such as Spotfire, R-shiny or similar вЂўWorking experience with open-source cheminformatics toolkits such as RDKit вЂўWorking experience with source-code management systems such as Git/github/bitbucket вЂўFamiliar with the foundational concepts in molecular biology, pharmacology or medicine. Working knowledge of medicinal chemistry and drug discovery is a plus Why consider Novartis? 750 million. ThatвЂ™s how many lives our products touch. And while weвЂ™re proud of that fact, in this world of digital and technological transformation, we must also ask ourselves this: how can we continue to improve and extend even more peopleвЂ™s lives? We believe the answers are found when curious, courageous and collaborative people like you are brought together in an inspiring environment. Where youвЂ™re given opportunities to explore the power of digital and data. Where youвЂ™re empowered to risk failure by taking smart risks, and where youвЂ™re surrounded by people who share your determination to tackle the worldвЂ™s toughest medical challenges. We are Novartis. Join us and help us reimagine medicine. Job Type Full Time Country USA Work Location Cambridge, MA Functional Area Research & Development Division NIBR Business Unit Global Discovery Chemistry Employment Type Regular Company/Legal Entity NIBRI EEO Statement The Novartis Group of Companies are Equal Opportunity Employers and take pride in maintaining a diverse environment. We do not discriminate in recruitment, hiring, training, promotion or any other employment practices for reasons of race, color, religion, gender, national origin, age, sexual orientation, marital or veteran status, disability, or any other legally protected status. Shift Work No | E33: 3.9 | F33: Novartis 3.9 | G33: Cambridge, MA | H33: Basel, Switzerland | I33: 10000+ employees | J33: 1996 | K33: Company - Public | L33: Biotech & Pharmaceuticals | M33: Biotech & Pharmaceuticals | N33: $10+ billion (USD) | O33: -1
A34: 32 | B34: Data Scientist | C34: $75K-$131K (Glassdoor est.) | D34: Cohere Health is simplifying healthcare for patients, their doctors, and all those who are important in a patient's healthcare experience. Our focus is to enable an efficient, transparent patient journey where patient goals are central to decision-making. We are a mission-driven and fast-growing company obsessed with eliminating the wasteful friction patients and doctors experience, particularly for diagnoses that require expensive procedures or medications. To that end, we build products and services that ensure the appropriate plan of care is understood and expeditiously approved, so that patients and doctors can focus on health, rather than payment or administrative hassles. This is a great opportunity for an outstanding data science professional to go in-house at a Series A healthcare technology company and learn what it takes to show the value of our products and services. You will work closely with analytics leadership, product and IT to support decision-making, and will dig into a wide range of strategic, product, and operational problems. The work will be fast-paced and project-based, with evolving needs - requiring scrappiness, flexibility, curiosity, and grace under pressure. Your work will enable Cohere to make the right investments in a critical stage for our company. This role offers the potential to grow at Cohere in data science, or potentially move to other functions as well. You will contribute to healthcare analytics from the economic and quality perspective, help build an a company, as well as wear many hats. Our team values empowerment and is committed to developing our talent. What you will do: Collaborate cross-functionally to design appropriate data-use capabilities across a wide breadth of analytical needs Use your expertise in healthcare data to develop effective models to improve our product Partner with Engineering to deliver seamless modeling for product implementation What you will have: 5-7 years model building and analytical experience at company where using ML/ AI were critical to the mission, preferably a healthcare company or allied health organization Direct experience partnering with Engineering to deliver the right analytical models to Product Clear understanding of model building, model maintenance and the measures that optimize models for product use Excellent communication and collaboration skills Proficient in R, SQL,Python and other common analytic/ data tools Strong knowledge of EMR data, SDoH, Claims, NLP use and other important healthcare related data sources Proficient in current modeling approaches in machine learning and AI such as decision trees and Med2Vec, Patient2vec and other innovative approaches to analyzing data Master's degree in STEM, public health, finance, economics, or other related field We can't wait to learn more about you and meet you at Cohere Health! | E34: 5 | F34: Cohere Health 5.0 | G34: Boston, MA | H34: Boston, MA | I34: 1 to 50 employees | J34: 2019 | K34: Company - Private | L34: IT Services | M34: Information Technology | N34: Unknown / Non-Applicable | O34: -1
A35: 33 | B35: Senior Research Statistician- Data Scientist | C35: $75K-$131K (Glassdoor est.) | D35: Acuity is seeking a Senior Research Statistician- Data Scientist to use statistical knowledge and research skills to solve business problems. The Research Statistician will develop, implement, and interpret statistical models with a strong emphasis on data mining and statistical/predictive modeling. Provides work direction. ESSENTIAL FUNCTIONS: Identifies and acquires additional data sources, both internal and external, that can be used to enhance analyses. Lead the development of analytical models to drive superior business outcomes. Develop in-depth understanding of drivers for optimization by utilizing statistics and data mining techniques. Using latest PC tools, develop, enhance and monitor reports and models for other business areas. Evaluate and use Data Mining Tools. Support, train, encourage, consult other areas in the company and provide actionable information to management. Continually monitor database information and future needs. Explore and acquire data from outside sources. Use database tools to support other departments Regular and predictable attendance. Perform other duties as assigned. EDUCATION: Masters/PhD in Statistics, Mathematics, Economics, Operations Research or Computer Science EXPERIENCE: 5 years P&C insurance, modelling and project leader experience. Programming skills including SAS and R. OTHER QUALIFICATIONS: Strong interpersonal, quantitative, problem-solving, computer and conceptual skills. Aptitude in predictive modeling, multivariate analysis, statistical modeling, data mining techniques and mathematical statistics. Ability to apply strong programming and data management skills. Knowledge of and experience with at least one major computer programming language or advanced syntax in a major statistical package. This job is classified as exempt. | E35: 4.8 | F35: Acuity Insurance 4.8 | G35: Sheboygan, WI | H35: Sheboygan, WI | I35: 1001 to 5000 employees | J35: 1925 | K35: Company - Private | L35: Insurance Carriers | M35: Insurance | N35: $1 to $2 billion (USD) | O35: -1
A36: 34 | B36: Data Engineer | C36: $75K-$131K (Glassdoor est.) | D36: Chef Software is the industry leader in IT automation and DevOps solutions. We develop the world's best products for managing applications and infrastructure at scale, and we deploy them against real problems in all kinds of industries. WeвЂ™re writing the rules of the cloud -- rules the worldвЂ™s top engineers live, breathe and contribute to. Our platform is used to enable hundreds of millions of people around the world to chat, fly, present, bank, game, shop, and learn. Chances are the web applications you use every day have infrastructure built, deployed, secured and ran with our code. We are a dynamic and rapidly growing software company with a strong sense of dedication to our customers and the Chef community. We work hard but try not to take ourselves too seriously. This is a very collaborative and inclusive work environment. Individuals, strong on aptitude and attitude, will have an opportunity to grow their professional careers through working with some of the most advanced technology and talented developers in the business. We provide competitive compensation, generous benefits, and a professional yet relaxed atmosphere. We are seeking a highly motivated, results oriented individual with strong data engineering skills and experience in cloud technologies to join our platform architecture team. This person will play a key role in developing advanced analytics products for Chef customers. They will also have a key influence on our future processes and architecture. What you'll do: Take ownership for designing, developing and maintaining scalable data pipelines and data models. Design, construct, install, test and maintain data management systems. Develop data ingestion and integrations processes. Ensure that all systems meet the business/company requirements as well as industry best practices. Integrate up-and-coming data management and software engineering technologies into existing data structures. Develop set processes for data mining, data modeling, data ingestion, and data production. Contribute to the design of new product offerings based on data analytics. Create custom software components and analytics applications. Research new uses for existing data; design experiments and analysis to answer key business questions. Employ an array of technologies, languages and tools to connect systems together. Collaborate with members of your team (eg, architects and engineers) on project goals. Recommend different ways to constantly improve data reliability and quality. Who you are: You have a minimum of a BachelorsвЂ™ degree in Computer Science, Data Science, or related field, plus 5 years of experience (or equivalent combination of education and experience). Masters degree in a relevant field is advantageous. You have demonstrable software development skills in at least one language such as Rust, Go, C#, C++, Ruby or Java. You have expertise in architecting, designing and implementing data solutions in a cloud-native environment (AWS preferred). You have experience with a variety of data technologies and structures that includes relational databases, NoSQL and graph. YouвЂ™re well-versed in working with big data. You have excellent analytical and problem-solving skills. You like to dive in, learn new things, and want to build awesome products. You have experience building and operating high-performance data systems. Working experience with Containers and Container orchestration tools such as Docker and Kubernetes is a huge plus. YouвЂ™ve had experience working with APIs (graph, specifically). You enjoy collaborating closely with product management and internal engineering teams to understand their complex issues, solve their problems and elicit frequent feedback on the solutions you provide You believe quality is part of the development process and not an afterthought Our platform architecture team is remote and distributed. Allowing us to not only live where we will be most productive, but enables us to create a work environment that celebrates all of our humanity. We celebrate the difference of perspective this brings and the barriers it removes. Benefits are awesome - a competitive salary, equity for all, solid medical/dental benefits, 401(k), telecommuting, flextime, a variety of interesting projects, and brilliant co-workers. At Chef, we celebrate and support our differences. We know employing a team rich in diverse thoughts, experiences, and opinions allows our employees, our products and our community to flourish. Chef is honored to be an equal opportunity workplace. We are dedicated to equal employment opportunities regardless of race, color, ancestry, religion, sex, national orientation, age, citizenship, marital status, disability, gender identity, sexual orientation or Veteran status. | E36: 3.6 | F36: Chef 3.6 | G36: United States | H36: Seattle, WA | I36: 201 to 500 employees | J36: 2008 | K36: Company - Private | L36: Enterprise Software & Network Solutions | M36: Information Technology | N36: $50 to $100 million (USD) | O36: Puppet, Ansible, SaltStack
A37: 35 | B37: Associate Data Scientist | C37: $75K-$131K (Glassdoor est.) | D37: Puget Sound Energy is looking to grow our community with like-minded, top talented individuals like you! With our rapidly growing, award winning energy efficiency programs, our pathway to an exciting and innovative future is now. PSE's IT Application Solutions team is looking for qualified candidates to fill an open Associate Data Scientist position! Job Description Puget Sound Energy is an electric and gas utility which provides homes and businesses throughout the Northwest. In order to meet and anticipate our customersвЂ™ needs, our Data Services team is expanding its team to include machine learning and data science technologies. In order to accomplish this we have an urgent need for an experienced Associate Data Scientist to work in our analytical Community of Practice, document internal standards, and to support our functional business areas. Job Responsibilities In addition to leading the development of our community, the Associate Data Scientist will be responsible for assisting with the design and development of an advanced analytical machine-learning-based software framework that can ingest, structure and model large amounts of data in different formats and from different sources, and is capable of learning, assisting and taking the initiative on various data modeling and analytical projects. These efforts may include the development of: Processes and data models that balance human judgment with machine intelligence Machine learning models to classify content in documents Proprietary document parsing and information extraction tools Data models and queries to organize and offer insights for users to help them understand Training models to guide other Community of Practice colleagues Data quality, cleansing and preparation of large structured, semi-structured or unstructured datasets for other groupsвЂ™ use Standards and Best Practice development Minimum Qualifications BachelorвЂ™s degree in Computer Science, Industrial Engineering, Business Administration or equivalent hands-on experience. General IT experience: 6+ years IT experience, including several years of systems development experience in the design and development of department-wide or enterprise-wide applications. Detailed understanding and 5+ years programming languages (specialized technical requirements as shown in attachment) and strong knowledge of office applications (e.g. Microsoft Office). Possesses full technical knowledge of phases of software development life cycle. Experience with at least two full life cycle implementations of a new application or purchased application. Extensive knowledge of multiple languages, i.e (specialized technical requirements as shown in attachment) environment, active business processes, business areas, as well as industry. Knowledge of systems and/or business analysis design concepts. Demonstrated proficiency in the applied use of systems and process analysis tools. Full system life cycle experience, including development lifecycle methodologies. Demonstrated understanding of Structured Query Language (SQL). Ability to facilitate interactive design and functional specification sessions. Highly developed interpersonal, written and verbal skills with an ability to express complex technical concepts in business terms. Excellent technical writing and system documentation skills. Strong analytical problem-solving, and conceptual skills. Demonstrated project management skills for moderate sized projects. Must be a вЂњteam playerвЂќ able to work with management in developing and implementing new processes and enabling systems. Able to work with end user groups to define application needs and identify feasible solutions. Proactive, self-motivated with the ability to motivate others and a customer-focused service attitude. Good organizational skills, with the ability to meet objectives and effectively multi-task. Ability to work with multiple levels of the organization, both technical and non-technical. Desired Qualifications 3 Years of hands-on data science experience Experience using source control tools like Git or Subversion Experience with developing analytical models within and across multiple data domains Proficient analytical and math background Demonstrated success in performing within a functional organizational environment Innovative mindset-thinks beyond the status quo Knowledge of OCR, Spark, Hadoop, H20 and/or cloud computing are preferred Tools like workflow Sketch Agenda (SKs) sheets and examples of risk mitigation Families and businesses depend on PSE to provide the energy they need to pursue their dreams. Our steadfast commitment to serving Washington communities with safe, dependable and efficient energy started in 1873. Today we're building the Northwest's energy future through efforts like our award winning energy efficiency programs and our leadership in renewable energy. At PSE we value and respect our employees and provide them opportunities to excel. We offer an expansive pay package that includes competitive compensation, annual goals-based incentive bonuses, comprehensive benefits, 401(K), a company paid retirement pension plan, and an employee assistance and wellness program. Puget Sound Energy is committed to providing equal employment opportunity to all qualified applicants. We do not discriminate on the basis of race, color, religion, sex, national origin, age, sexual orientation, gender identity, marital status, veteran status or presence of a disability that with or without reasonable accommodation does not prevent performance of the essential functions of the job. Should you have a disability that requires assistance and/or reasonable accommodation with the job application process, please contact the Human Resources Staffing department at jobs@pse.com or 425-462-3017. Nearest Major Market: Seattle Nearest Secondary Market: Bellevue | E37: 3.3 | F37: Puget Sound Energy 3.3 | G37: Bothell, WA | H37: Bellevue, WA | I37: 1001 to 5000 employees | J37: 1999 | K37: Company - Private | L37: Utilities | M37: Oil, Gas, Energy & Utilities | N37: $2 to $5 billion (USD) | O37: -1
A38: 36 | B38: Business Intelligence Analyst | C38: $75K-$131K (Glassdoor est.) | D38: The Business Intelligence Analyst is responsible for analyzing and reviewing data that is collected in our current and future products and services. Working with our Data Scientist team, the Business Intelligence Analyst would need to be able to take this data and apply to the markets our products are in for us to better serve our customers. This position will require a high degree of attention to detail along with ability to review calculations for quality assurance. The Business Intelligence Analyst must have good communication and organization skills, along with a working knowledge of day to day operations and priorities within their department and the company. Troubleshooting and problem solving issues, as well as working closely with managers and developers, to solve these problems, will be needed. Another responsibility could include creating internal reporting features to streamline information processing and sharing throughout the company. This position requires a high level of expertise with Microsoft Excel, and skills in SQL, Tableau, Microsoft Power BI, and/or R/Python are preferred. Assume other duties as assigned. | E38: 2.7 | F38: Sandhills Global 2.7 | G38: Lincoln, NE | H38: Lincoln, NE | I38: 1001 to 5000 employees | J38: 1978 | K38: Company - Private | L38: Enterprise Software & Network Solutions | M38: Information Technology | N38: $50 to $100 million (USD) | O38: -1
A39: 37 | B39: Data Scientist | C39: $75K-$131K (Glassdoor est.) | D39: Join Our Growing Team A career with A Place for Mom is an opportunity for you to join a rapidly expanding company committed to making a difference for seniors and their families. A Place for Mom is an online platform connecting families searching for senior care services with a team of experienced advisors providing insight-driven and personalized solutions. Our mission, as the leader in senior care advisory, is to be a trusted destination for families and our community customers. We are a quickly growing organization with over 500 advisors connecting more than 300K families every year to one of our community customers. Living by our values and working to achieve excellence on behalf of our customers is integral to success at A Place for Mom. Employees who thrive at A Place for Mom live our values every day and are an important part of our hiring practices: Focus on Excellence Act with Integrity & Assume Positive Intent Drive Outcomes Every Day with Passion and A Sense of Mission Make the Lives of our Families and Customers Better, Easier and More Successful Realize the Full Potential in Each Team Member. Work as a Single Supportive Team The Position Based in New York, NY or Overland Park, KS, the Data Scientist builds prediction algorithms that help serves families and our senior living community customers more efficiently. This position will support the sales teams in our efforts to drive continued market share growth. The Data Scientist will work within the Commercial Operations team to increase efficiency and improve the customer experience through the application of statistics and machine learning. This position will support the Sales & Operations teams in our efforts to drive greater market share, improve move-in conversion and grow our bottom line. Who You Are You are a self-starter who is passionate about increasing efficiency and improving the customer experience through the application of statistics and machine learning. You are able to work independently and lead efforts to drive lead prioritization, customer segmentation, enhanced data analysis, experimental design & testing, business intelligence, and business reporting. You are a strong communicator and enjoy working with talented and driven people that will challenge you to reach the next level. Incorporate APFM Values into each customer and co-worker interaction Design implement and maintain models that optimize the customer experience and help our sales team prioritize the right leads at the right time Develop predictive models that balance accuracy with human interpretability and help evaluate and improve the early stages of the sales funnel Deign experiments to test the impact of models on customer conversion and other metrics Evolve a Random Forest based model that sorts leads near the end of their journey through the sales process Manage & monitor the day to day operation of the servers running existing models and their connection to data repositories Develop and evaluate models that segment customers at a number of steps along the sales process, with the ultimate goal of improving the customerвЂ™s experience through segmentation Operate and maintain tools that combine disparate data sources and are written in python and R while developing novel ways to utilize the vast amounts of data that APFM maintains Collaborate with teams throughout APFM to identify the appropriate metrics, define effective test groups, design experiments, calculate samples sizes and evaluate the results of these tests Investigate business problems and validate assumptions through statistical analysis Assist the analyst team in generating reports, troubleshooting reports and pulling data to better understand Commercial Operations and Sales trends & performance Act as the primary lead for the teamвЂ™s machine learning and statistics who can define a path forward to address business questions in these areas As the team grows and the need for statistics and machine learning increases we anticipate that the Data Scientist will manage at least one data analyst 2+ years applying statistical and machine-learning methods to solve business problems Strong SQL skills Strong Python programming skills; additional experience in R nice to have but not required Experience maintaining code repositories in git Sharp problems solving skills and strong statistics skills Strong fundamentals and intuition in applied statistics for both prediction and explanation Able to build, optimize, and test prediction and forecasting models Familiarity with basic Linux tools Able to quickly understand business problems and implement experimental designs Able to balance analytical rigor against meeting deadlines Knowledge of causal analysis methods Excellent presentation, writing, and data visualization skills Experience using AWS to implement data science workflows is a plus Experience working with product managers and business stakeholders to build products driven by prediction models and insights from data analysis Ability to convey machine learning and statistics concepts to non-experts Education Requirements. BachelorвЂ™s degree in technical field required. Compensation The position is a salaried, exempt position. #LI-AR1 | E39: 2.7 | F39: A Place for Mom 2.7 | G39: Overland Park, KS | H39: New York, NY | I39: 501 to 1000 employees | J39: 2000 | K39: Company - Private | L39: Health Care Services & Hospitals | M39: Health Care | N39: Unknown / Non-Applicable | O39: Enlivant, Sunrise Senior Living, Brookdale Senior Living
A40: 38 | B40: Data Scientist | C40: $75K-$131K (Glassdoor est.) | D40: Job Title: Data Scientists Job Description Join an elite group dedicated to continuous personal improvement as GCT is currently seeking Data Scientists of all levels to support an intelligence agency with insights gained from analyzing voluminous sensor data. The ideal candidate is adept at using large data sets to find opportunities for process optimization and using models to test the effectiveness of different courses of action. Candidates must have strong experience using a variety of data mining/data analysis methods, using a variety of data tools, building and implementing models, using/creating algorithms and creating/running simulations. The right candidate will have a passion for discovering solutions hidden in large data sets and working with stakeholders to improve business outcomes. Clearance: TS/SCI w/Full scope polygraph (or used within the past 24 months) Education/Experience Requirements Senior Positions: Masters degree in Data Science, Statistics, Mathematics, Computer Science or another quantitative field, or extensive comparable experience 10+ years of relevant experience Junior/Intermediate Positions Completed B.S. in Data Science, Mathematics, Statistics, Computer Science, Computer Engineering, or a closely related technical field 3-9 years of relevant experience Qualifications Experience using statistical computer languages (SAS, SPSS, R, Python, SLQ, etc.) to manipulate data and draw insights fromlarge data sets Experience working with and creating data architectures Knowledge of a variety of machine learning techniques (clustering, decision tree learning, artificial neural networks, etc.) and their real-world advantages/drawbacks Knowledge of advanced statistical techniques and concepts (regression, properties of distributions, statistical tests and proper usage, etc.) and experience with applications Excellent written and verbal communication skills Strong problem solving skills A drive to learn and master new technologies and techniques Desired Skills Experience manipulating data sets and building statistical models Coding knowledge and experience with several languages: C, C++, Java, JavaScript, etc. Knowledge and experience in statistical and data mining techniques: GLM/Regression, Random Forest, Boosting, Trees, text mining, social network analysis, Bayes, etc. Experience querying databases and using statistical computer languages: R, Python, SLQ, etc. Experience using web services: Redshift, S3, Spark, DigitalOcean, AWS, etc. Experience creating and using advanced machine learning algorithms and statistics: regression, simulation, scenario analysis, modeling, clustering, decision trees, neural networks, etc. Experience analyzing data from 3rd party providers: Google Analytics, Site Catalyst, Coremetrics, Adwords, Crimson Hexagon, Facebook Insights, etc. Experience with distributed data/computing tools: Map/Reduce, Hadoop, Hive, Spark, Gurobi, MySQL, etc. Experience visualizing/presenting data for stakeholders using: Periscope, Business Objects, D3, ggplot, etc. The success of Great-Circle Technologies depends on the success and well-being of its employees. GCT promotes work/life balance and encourages the overall well-being of each of its contributors. A comprehensive benefits package is provided, which currently includes company paid single medical, dental, life, disability, and long-term care insurances (with contributions to family premiums,) matching 401k plan, 34 days off per year including 10 Federal holidays plus the day after Thanksgiving, Christmas and New YearвЂ™s eves! Join us at Great-Circle Technologies, where innovation is the shortest distance between two points. Great-Circle Technologies is an Equal Opportunity Employer. Great-Circle Technologies ensures all qualified applicants will receive consideration for employment without regard to gender, race, ethnic background, religion, disability, sexual orientation, gender identity, national origin, age, or protected veteran status. | E40: 2.2 | F40: Great-Circle Technologies 2.2 | G40: Chantilly, VA | H40: Chantilly, VA | I40: 1 to 50 employees | J40: 2000 | K40: Company - Private | L40: Enterprise Software & Network Solutions | M40: Information Technology | N40: $1 to $5 million (USD) | O40: -1
A41: 39 | B41: Senior Analyst/Data Scientist | C41: $75K-$131K (Glassdoor est.) | D41: At Edmunds were driven to make car buying easier. Ever since we began publishing printed car guides in the 60s, the company has been in the business of trust, innovating ways to empower and support car shoppers. When Edmunds launched the car industrys first Internet site in 1994, we established a leadership position online and have never looked back. Now, as one of the most trusted review sites on the Internet, millions of visitors use our research, shopping and buying tools every month to make an easy and informed decision on their next car. For consumers, we bring peace of mind. For dealers, we make tools to help them solve their problems and sell more cars. How do we do it, you ask? The key ingredients are our enthusiastic employees, progressive company culture and cutting-edge technology. Want to join the team? Read on to find out how! What Youre Applying For: Edmunds is seeking a skilled, creative and enthusiastic Senior Analyst/Data Scientist experienced in generating actionable insights from large sets of data, measuring business performance, and identifying areas of growth and optimization using advanced analytical (modeling) and experimental approaches. The Senior Analyst/Data Scientist will serve a hybrid role in supporting our Tier 3 Sales team by creating dealer performance forecasts; monitoring revenue, dealer penetration and churn, analyzing effectiveness of sales efforts, and identifying areas of optimization and growth by extracting insights through modeling, testing and experimentation. In addition, the Senior Analyst/Data Scientist will also lead data science projects focused on creating and fine-tuning models to reduce churn of our T3 business as well as maintaining and optimizing existing traffic forecast models for the business. The Senior Analyst/Data Scientist will also be expected to design, conduct, and lead complex analyses with minimal guidance to address questions from our executive team and show keen ability to interpret and communicate findings via a presentation in a clear, concise and meaningful manner. In addition, this person will be expected to take ownership of projects to continually improve reporting quality through automation and be able to anticipate and prevent problems and roadblocks before they occur. This is a great opportunity for an individual with significant business acumen that is interested in playing with the wealth of structured and unstructured data that is available within the car buying ecosystem. Curiosity and business intellect a must. What Youll Do: Partner with senior business stakeholders to help optimize on our core business KPIs. Design, conduct and lead complex analyses that mine, extract, track, report and analyze performance metrics Apply analytical rigor and statistical methods to analyze large amounts of data, using advanced statistical techniques such as predictive statistical models, customer profiling, segmentation analysis, survey design and analysis and data mining. Provide updates on the performance of our core KPIs as well as insights and recommendations to both our senior stakeholders and executive team in a presentation. Create and produce forecasts, reports, ad hoc requests, dashboards, etc. utilizing our data warehouse and other data source systems and summarize your findings Develop, evaluate, refine, and automate analytic models using data to address business needs, and identify areas of optimization. Collaborate with different departments and define requirements to improve our reporting suite What You Need: A passion for analytics Strong analytical and data mining skills Strong data extraction and manipulation skills - SQL experience required Data modeling / statistical analysis / predictive modeling experience is required. (R or Python) Experience creating reports and dashboards through BI tools such as Tableau is required Excellent presentation and communication skills Proven ability to accurately report and interpret trends and translate these trends into actionable insights. Proven ability to synthesize complex data/analysis into clear and concise insights and recommendations. Ability to multitask and to balance competing priorities. Masters degree in a quantitative field, such as mathematics, statistics, physics, computer science, business analytics, etc. with at least three years of related work experience, or a BS in related field with at least five years of relevant work experience Working @ Edmunds.com: Employees think its a pretty great place to work and some pretty impressive publications think it is too: we have been recognized as one of the best places to work by the Fortune Magazine and Great Places to Work, LA Business Journal, Computerworld, and Built in LA. We've also been identified as one of the best workplaces specifically in Technology and also for Diversity and Asian Americans. In fact, our CEO, Avi Steinlauf, was rated as one of Glassdoor's Highest Rated CEOs! If youre interested in learning more and joining our mission, wed love to hear from you! Edmunds will consider for employment qualified candidates with criminal histories in a manner consistent with the requirements of all applicable laws. *LI-DNP | E41: 3.4 | F41: Edmunds.com 3.4 | G41: Santa Monica, CA | H41: Santa Monica, CA | I41: 501 to 1000 employees | J41: 1966 | K41: Company - Private | L41: Internet | M41: Information Technology | N41: $100 to $500 million (USD) | O41: TrueCar, Cars.com, Kelley Blue Book
A42: 40 | B42: Data Analyst | C42: $75K-$131K (Glassdoor est.) | D42: Data Analyst Location Boston Business Function Portfolio Services Apply Now Job Description: Enterprise Data Support Services is a newly formulated centralized group that is going to play a pivotal role in building the next generation of tools and platforms to address the data needs for end users and applications through the creation, maintenance and use of an Enterprise level data platform. This platform is being built to not only support data but also provide capabilities of centralized calculation engines for data accuracy and data consistency. This position reports into the Manager of Enterprise Data Support Services as part of the organization under the Chief Data Officer. The Data Analyst will serve as a flexible generalist by providing data analysis and analytical insight based on the requests from Investment and Business Development teams. The individual will utilize data analysis tools such as Excel, SQL, R or Python to collate data from various sources, analyze the information and provide insights and analysis to the requesting teams. In conjunction with IT, the individual will verify any new data being added to the Central Data Repository to sign-off on data completeness and accuracy from a business domain perspective. Principal Duties : Work with investment teams to understand their data needs and translate them into a process to collate and analyze data to provide insights Use statistical models and industry recognized investment data calculation methodologies to perform various data analytics in SQL and MS Excel Exercise relational database knowledge to construct and execute SQL queries to be used in data analysis activities Use other tools such as R and Python to manipulate data to address the information needs across the organization Build and maintain strong relationships across the firm to understand CAвЂ™s business goals and prepare for the organizationвЂ™s evolving data needs Contribute to additional projects where relevant domain or data analysis expertise is needed Qualifications: BachelorвЂ™s Degree, with preference to Data Analytics, Information Systems, or Mathematics Demonstrated skill in SQL usage as part of data analysis Working knowledge of R or Python is desirable Working knowledge of relational database design concepts Demonstrated track record of working autonomously in a highly-productive environment, executing with comfort in gray areas, and executing across multiple competing deadlines with fast-paced delivery targets Excellent organizational, written and verbal communication skills Willingness to learn and embrace a вЂjack of all tradesвЂ™ mentality to build expertise and data depth across the entire Enterprise Data Support Services product suite Demonstrated progression towards CIPM, CFA, and/or CAIA certification is a big plus Direct experience integrating data from multiple sources such as client, fund, and market data domains strongly preferred | E42: 3.1 | F42: Cambridge Associates, LLC 3.1 | G42: Boston, MA | H42: Boston, MA | I42: 501 to 1000 employees | J42: 1973 | K42: Company - Private | L42: Investment Banking & Asset Management | M42: Finance | N42: $100 to $500 million (USD) | O42: -1
A43: 41 | B43: Machine Learning Engineer | C43: $75K-$131K (Glassdoor est.) | D43: We deliver our customers peace of mind every day by helping them protect what they value most. Our passion for placing the customer at the center of everything we do is driving a transformational shift at Liberty Mutual. Operating as a tech startup within a Fortune 100 company, we are leading a digital disruption that will redefine how people experience insurance. Job Introduction: The Analytic Platform and Service organization is looking to hire a Machine Learning Engineer to their team. This candidate will participate in the software development within an Agile team and work on the internally developed analytics application. About the job: Build out our Real Time Scoring platform and working with our data scientist partners to support the deployment of predictive models and deliver business value from AI and Machine Learning. Develop Java application that is intended to allow analytics teams to quickly create, manage and terminate their own scalable high-performance cloud computing and storage environments to support analytics, machine learning and big data projects. Work directly with data science teams in all markets to assist them with their projects and gather new requirements and insights to support the ongoing development. Respond quickly to change, pick up new technologies and adapt to changing requirements. Demonstrate competence at writing, testing and debugging Python and Java code. Desired skills: Bachelor's or Master's degree in technical or business discipline or equivalent experience. Minimum 2+ years of professional development experience in Python and Java. Foundational knowledge or proficient with data science and machine learning tools and techniques Experience in new and emerging technologies such as AWS, Azure and Cloud, DevOps, CI/CD and Microservices. Excellent analytical, problem solving, and communication and collaboration skills. General knowledge of agile software development concepts and processes. Must be proactive, demonstrate initiative and be a logical thinker. Experience with layered system architectures and layered solutions; understanding of shared software concepts. Highly competitive candidates will have: R Language Spark Go Language We take care of our employees... We strongly believe that a great job should keep you happy both at work-and in life. That's why we offer: Workplace Flexibility Wellness Perks Collaborative workspaces Sit/stand desks Career development, programs and classes Diversity & Inclusion programs Commuter Benefits Adoption Assistance College Savings Plan Education reimbursement Hackathon Events Liberty Mutual was named as a '2016 Great Place to Work' by Great Place to Work US. For more info about our benefits - https://libertymutualgroup.com/careers/working-here/benefits Learn more about Tech at Liberty Mutual - http://www.jobs.libertymutualgroup.com/careers/technology-jobs Check out our Tech at Liberty Mutual YouTube playlist - https://www.youtube.com/playlist?list=PLxUNmyJ_IIGx9yoUJfQ8k5APAK3-KAa6j | E43: 3.4 | F43: Liberty Mutual Insurance 3.4 | G43: Portsmouth, NH | H43: Boston, MA | I43: 10000+ employees | J43: 1912 | K43: Company - Private | L43: Insurance Carriers | M43: Insurance | N43: $10+ billion (USD) | O43: Travelers, Allstate, State Farm
A44: 42 | B44: Data Analyst I | C44: $75K-$131K (Glassdoor est.) | D44: Who is Cenlar? You are. Employee-owners have made Cenlar one of the nationвЂ™s largest mortgage subservicers. We have achieved success by empowering people with company ownership, real programs that provide avenues for advancement, and a great atmosphere that makes everyone look forward to the workday. Get your share of our success by considering the opportunity to join our team as a Data Analyst I. Job Summary: Responsible for working with large and complex data sets (both internal and external data) to evaluate, recommend, and support the implementation of business strategies. Identifies and compiles data sets using a variety of tools (e.g. SQL, Access) to help predict, improve, and measure the success of key business to business outcomes. Responsible for documenting data requirements, data collection/processing/cleaning, and exploratory data analysis; which may include utilizing statistical models/algorithms and data visualization techniques. Incumbents in this role may often be referred to as Data Scientists. Responsibilities: Day-to-day actions are focused on administering defined procedures, analysis and report preparation. Commands knowledge of data elements across the enterprise and industry вЂ“ definitions, lineage and usage Executes creation of tabular operational reports and aggregation reports with medium to high complexity. Commands intermediate to expert level t-SQL coding proficiency Performs data mapping for systems integration, data provisioning, and data consumption Responsible for documenting metadata, data lineage, data definitions and business glossary entries. Handles basic data transformation tasks such as date and decimal formatting, rounding of numeric values, and conversion of numeric values to percentages. Has intermediate to expert level SSIS ETL build proficiency Works with Data stewards to enforce adherence to standards for enhancements and new repositories. Qualifications: Experienced professional with relevant and current skills (3-5 years). Primary focus is on daily deliverable of routine and defined outputs, while at the same time developing knowledge of the broader context in which the work is being performed. BachelorвЂ™s degree in computer science, finance, mathematics, statistics (or similar) or equivalent work experience Total Rewards: Cenlar FSB offers outstanding benefits which may include paid medical/dental/life insurance, 401k, employee ownership, tuition assistance, a supportive work environment, and genuine opportunities for advancement. Cenlar is a Drug Free Workplace and an Equal Employment Opportunity/Affirmative Action Employer -- M/F/D/V/SO. Visit www.cenlar.com for more details. Please apply online. | E44: 2.6 | F44: Cenlar 2.6 | G44: Ewing, NJ | H44: Ewing, NJ | I44: 1001 to 5000 employees | J44: 1958 | K44: Company - Private | L44: -1 | M44: -1 | N44: $100 to $500 million (USD) | O44: -1
A45: 43 | B45: Scientist - Molecular Biology | C45: $75K-$131K (Glassdoor est.) | D45: ArsenalBioвЂ™s mission is to develop efficacious and safe cellular therapies for patients with chronic diseases, initially cancer. Our products are being designed to herald the transition of adoptive cell therapy from a hospital based treatment to outpatient therapy, like most other cancer treatments. Our people are our greatest asset, they bring scientific talents in molecular biology, immunology, pharmacology, protein chemistry, computational biology, automation, genome engineering, software and other fields to make the future happen now. What You Will Do: Lead the development, application and optimization of DNA constructs for genetic modification of cell lines and primary immune cells Design and develop DNA constructs and libraries encoding affinity reagents, receptors and synthetic circuits for high-throughput functional screens Work with interdisciplinary teams to establish and test novel adoptive cell therapy approaches Provide expert support for molecular biology applications and strategies to the broader scientific team Maintain familiarity with the relevant current literature and its application to synthetic biology and genome engineering Coordinate tasks across multiple projects, demonstrating prioritization and planning Interpret and effectively execute experiments in line with project timelines and goals Mentor research associates within the group in areas of technical expertise What You Will Bring: PhD in molecular biology or a related field, with 3+ years of relevant research experience in industry or academia Experience developing/optimizing protocols for nucleic acid cloning, amplification, modification and analysis Experience optimizing/developing protocols for DNA assembly and library constructions for applications such as synthetic biology, functional genomics and/or protein engineering Working knowledge of vector design for gene expression, genetic reporter systems and genome engineering applications Working knowledge of next-generation sequencing technologies and workflows Working knowledge of automation and workflows Entrepreneurial behaviors demonstrated by agility, accountability, transparency, resourcefulness, and ability to get things done Ability to quickly learn new skills and knowledge on the job, demonstrate productivity, and deliver high-quality results Flexible mind with ability to think outside the box, creative approach to problem solving, and comfort in working with ambiguous data in an open-ended, exploratory process We are an equal opportunity employer and value diversity at our company. We do not discriminate on the basis of race, religion, color, national origin, gender, sexual orientation, age, marital status, veteran status, or disability status To all recruitment agencies: ArsenalBio does not accept agency resumes. Please do not forward resumes to our jobs alias, or Arsenalbio employees. ArsenalBio is not responsible for any fees related to unsolicited resumes. | E45: 5 | F45: Arsenal Biosciences 5.0 | G45: South San Francisco, CA | H45: South San Francisco, CA | I45: 51 to 200 employees | J45: 2019 | K45: Company - Private | L45: Biotech & Pharmaceuticals | M45: Biotech & Pharmaceuticals | N45: Unknown / Non-Applicable | O45: -1
A46: 44 | B46: Data Scientist | C46: $75K-$131K (Glassdoor est.) | D46: The Opportunity Eversight is the recognized leader in AI-powered price and promotions. Eversight's proprietary cloud-based SaaS solution brings AI and continuous experimentation to consumer brands and retailers. Our software acts as a coach, enabling market leaders to transform pricing and promotion strategy for the $3.4 trillion spent in consumer goods retail using intelligent, real-time data and insights. Reporting directly to the Head of Data Science, you will be at the center of what determines Eversight's success as a company. You will analyze the data and develop production code using the newest Data Science and Machine Learning techniques to determine the optimal prices and promotions for major product manufacturers and retailers that sell these products. Responsibilities Research, implement and modify modern Data Science techniques. More specifically: Build Statistical and Machine Learning models that describe the impact of prices and promotions on shopper behavior, including behavioral pricing effects. You'll need to find middle ground between using flexible modern AI methods and proven classical methods. Develop Optimization and Experiment Design systems, which determine the best prices to set for each product in each store each week. Finding a good balance on the exploration-exploitation tradeoff will be crucial. Design and run pricing experiments across hundreds of stores and tens of thousands of products Create model validation methods to make sure that our models are accurate and to quantify the impact of our solutions on the clients' bottom line Work with Product Management to generate ideas and quickly turn them into efficient, well-tested, functioning code (we mostly use Python) Partner with the Engineering team to create highly scalable solutions Serve as Data Science expert both within Eversight and for our clients Lead custom analyses and connect them to actionable Business and Product insights Help prioritize new feature development by assessing potential impact Be a go-to resource for science-related questions about the product Behavioral Profile Analytical, framework thinker Comfortable in a fast-paced environment Highly collaborative Strong at translating Data Science concepts to non-technical audiences Business focused; measures work in its contributions to business outcomes and prioritizes effort against deliverables accordingly Skills and Experience M.S. in Operations Research, Machine Learning, Statistics, Mathematics, Engineering, Economics, Computer Science or relevant quantitative field 2+ years of experience in Data Science or Machine Learning. Ph.D. experience accepted Elite ability in : Linear Algebra, Hypothesis Testing, Bayesian Methods, Regressions, Calculus, Maximum Likelihood Estimation Experience in Machine Learning methods: Neural Networks (Deep Learning, Embeddings, Sequence Modeling, CNN), Tree-based methods (GBDT, Random Forest), Regressions (Linear, GLM), Regularization Methods (L1/L2 penalties, Feature Selection, Dimensionality Reduction) Experience in A/B testing and Design of Experiments preferred Demand Modeling, Pricing, and Causal Inference experience preferred but optional Knowledge of common data structures and ability to write efficient code in Python Agile experience preferred Location Palo Alto, CA About the Company Eversight is the recognized leader in AI-powered pricing and promotions. Global brands and retailers rely on the Eversight platform to optimize pricing in response to market conditions and to deliver higher ROI on promotional spend. Eversight's Pricing Suite and Offer Innovation Suite solutions are driving strong margin and sales volume improvements for leading companies such as Coca-Cola, Frito-Lay, Raley's, and Rite Aid. Founded in 2013, Eversight is headquartered in Palo Alto, California, with offices in Chicago and New York. | E46: 4.2 | F46: Eversight 4.2 | G46: Palo Alto, CA | H46: Palo Alto, CA | I46: 51 to 200 employees | J46: 2013 | K46: Company - Private | L46: Enterprise Software & Network Solutions | M46: Information Technology | N46: $10 to $25 million (USD) | O46: -1
A47: 45 | B47: Computational Scientist, Machine Learning | C47: $75K-$131K (Glassdoor est.) | D47: ROLE SUMMARY The Pfizer Simulation and Modeling Sciences (SMS) group has an opening for a computational methods developer with strong expertise in computational biology, bioinformatics, Artificial Intelligence (AI) and Machine Learning (ML). Working with the biotherapeutics group, the successful candidate will leverage skills in sequence analysis, protein structure modeling, machine learning, and scientific programming to develop AI models and computational tools that enable design of antibody therapeutics and prediction of biophysical and therapeutic properties. To be successful in this role, the incumbent must be able to effectively collaborate with colleagues with diverse scientific background, identify problems and opportunities, and combine techniques from computational biology and AI, in particular recent advances in deep learning, to rapidly develop powerful computational solutions. ROLE RESPONSIBILITIES Identify novel and creative applications of deep learning approaches to advance discovery and development of antibody therapeutics. Collaborate across biotherapeutics organization to implement powerful AI models and cutting-edge computational tools to enable rapid developability assessment of novel monoclonal antibodies. Effectively utilize relevant public and proprietary databases and available computational resources (internal HPC and Cloud) to develop ML models to predict important biophysical and therapeutic properties of antibodies. Occasionally contribute to the ongoing and new ML-related efforts within SMS in the area of small molecule discovery and development. Leverage proprietary computational framework and applications to deploy AI/ML models for wide usage by Pfizer scientists. Proactively identify, assess, and internalize promising methods and tools. Communicate and explain computational models and ML techniques to broad scientific audience from diverse discipline. BASIC QUALIFICATIONS Ph.D. in computational biology, chemical engineering, computer science, physical or biological sciences, machine learning, or related discipline. Experience with several machine learning algorithms (e.g. Random Forest, Support Vector Machine, Deep Neural Networks) and packages (e.g. Sci-kit Learn, Keras, TensorFlow, PyTorch). Track record of applying machine learning, in particular modern deep learning approaches, to solve relevant biological problems. Familiarity with concepts, techniques, and common tools used for sequence analysis and protein structure modeling. Experience with Unix/Linux, HPC environments, and high-level programming language (e.g. Python). Excellent communication and interpersonal skills. PREFERRED QUALIFICATIONS Demonstrated track record of applying AI/ML, in particular cutting-edge deep learning techniques such as ConvNet, RNN, generative modeling, and reinforcement learning to tackle complex drug discovery and development problems. Experience in applying ML to immunology data, e.g. HLA peptide binding. OTHER INFORMATION Last Date to Apply for Job: July 6, 2020 Eligible for Employee Referral Bonus #LI-PFE Sunshine Act Pfizer reports payments and other transfers of value to health care providers as required by federal and state transparency laws and implementing regulations. These laws and regulations require Pfizer to provide government agencies with information such as a health care providerвЂ™s name, address and the type of payments or other value received, generally for public disclosure. Subject to further legal review and statutory or regulatory clarification, which Pfizer intends to pursue, reimbursement of recruiting expenses for licensed physicians may constitute a reportable transfer of value under the federal transparency law commonly known as the Sunshine Act. Therefore, if you are a licensed physician who incurs recruiting expenses as a result of interviewing with Pfizer that we pay or reimburse, your name, address and the amount of payments made currently will be reported to the government. If you have questions regarding this matter, please do not hesitate to contact your Talent Acquisition representative. EEO & Employment Eligibility Pfizer is committed to equal opportunity in the terms and conditions of employment for all employees and job applicants without regard to race, color, religion, sex, sexual orientation, age, gender identity or gender expression, national origin, disability or veteran status. Pfizer also complies with all applicable national, state and local laws governing nondiscrimination in employment as well as work authorization and employment eligibility verification requirements of the Immigration and Nationality Act and IRCA. Pfizer is an E-Verify employer. Information & Business Tech | E47: 4.1 | F47: Pfizer 4.1 | G47: Cambridge, MA | H47: New York, NY | I47: 10000+ employees | J47: 1849 | K47: Company - Public | L47: Biotech & Pharmaceuticals | M47: Biotech & Pharmaceuticals | N47: $10+ billion (USD) | O47: -1
A48: 46 | B48: Senior Data Scientist | C48: $75K-$131K (Glassdoor est.) | D48: Klaviyo is looking for Senior Data Scientists to join our team which is still in its early days. You'll have a big impact on our direction and how we operate. You'll be central to upfront research and shipping products that help our customers learn and grow from their data. The ideal candidate has a background in data science, statistics and machine learning and has done work ranging from exploratory analysis to training and deploying models. We use a wide variety of data mining and machine learning algorithms. The right candidate will have both a solid fundamental understanding and deep practical experience with at least a few modeling and machine learning techniques. You should have experience building models that are used by people to make better decisions. We're focused on shipping early and often. We prefer iterative solutions that are incrementally better to the perfect solution. How you will make a difference: Analyze large data sets (we're collecting billions of individual actions every month). Build models and ship products that enable businesses to grow faster and communicate with their customers. Democratize and open up that technology to everyone (Our background as a team is building these models for the Fortune 50). Match the right assumptions and models to the right problem. Measure and know what impact your models had on the decisions people made -- e.g. did they outperform the previous best model or a human decision maker? Who You Are: Bachelor's or advanced degree in statistics, applied mathematics, computer science or other relevant quantitative discipline, or equivalent industry experience. Have worked in a data science role for 5+ years professionally or academically and can talk about your projects and the techniques you used. Have a strong fundamental understanding and deep experience with at least a few machine learning algorithms (e.g. regressions, decision trees, k-means clustering, neural networks). Understand Bayesian modeling techniques. Are capable of analyzing data and making rigorous statements about what can or cannot be concluded. Have experience designing and implementing model performance/validation assessments. Have a background in statistics and understand different distributions and the conditions under which they're valid. Know how code and have used data science tools and packages. Have demonstrated a measurable impact based on the models you've created. It's not always easy getting a model correct and we love talking about places we got stuck and working as a team to think through ideas that could unblock us. Have a desire to ship features powered by data science (in other words, you're excited by both upfront research and actually getting models into production at cloud scale). Get to know Klaviyo Klaviyo is the world's leading owned marketing platform known for accelerating revenue for online businesses using the channels they own like email, web, and mobile. Enabling companies to leverage these owned marketing channels, Klaviyo makes it easy to store, access, analyze and use transactional and behavioral data to power highly-targeted customer and prospect communications. And unlike other marketing platforms, Klaviyo doesn't force companies to compromise between advanced functionality or ease of use - so companies of all sizes are able to maximize their sales quickly. That's why over 28,000+ innovative companies like Unilever, Custom Ink and Eventbrite sell more with Klaviyo. | E48: 4.8 | F48: Klaviyo 4.8 | G48: Boston, MA | H48: Boston, MA | I48: 201 to 500 employees | J48: 2012 | K48: Company - Private | L48: Computer Hardware & Software | M48: Information Technology | N48: Unknown / Non-Applicable | O48: -1
A49: 47 | B49: Data Scientist | C49: $75K-$131K (Glassdoor est.) | D49: Job Description The Cooking Lab is the publisher of both Modernist Cuisine: The Art and Science of Cooking (2011) and Modernist Cuisine at Home (2012). Our interdisciplinary team in Bellevue, Washington includes scientists, development chefs, and a full editorial department, as well as business and marketing staffвЂ”all dedicated to advancing the state of the culinary arts through the creative application of scientific knowledge and experimental techniques. In addition to our award-winning Modernist Cuisine books, The Cooking Lab provides consulting, R & D, and invention services to food companies and culinary equipment makers, large and small. Our research laboratory in Bellevue includes one of the best equipped kitchens in the world as well as access to a full set of machining, analytical, and computational facilities, provided by the Intellectual Ventures Lab. The Cooking Lab is looking for a Data Scientist to join their journey to understand food and cooking. In addition to its primary research, MC is very interested in analyzing the received wisdom of recipes from around the world and over time. The Data Scientist will be responsible for leading an audacious effort to catalog, ingest, and analyze the world's pastry recipes. The Data Scientist will apply computer vision, OCR, natural language processing, and other techniques to transform formatted recipes into structured data. He or she will lead further development of our pipeline for tagging unstructured data to train machine learning algorithms to identify new recipes. Then, he or she will perform analysis on the resulting structured data to answer specific questions about the data. For instance, "What is the distribution of baking temperatures recommended for a croissant?" Or, "How has the amount of salt in chocolate chip cookie recipes varied over time?" In addition to the recipe analysis responsibilities, the Data Scientist will work with the culinary team for a variety of other scientific analysis and visualization projects. Responsibilities: Expand our in-house framework for catalog of pastry recipes Further develop our methodology for schematizing, codifying, and analyzing recipes Implement processes, including human tagging, machine learning, and quality evaluation for codified recipes Mine data for useful insights and storytelling Support culinary team in scientific analysis and visualization projects Key Qualifications and Required Skills: Experience with natural language processing and machine learning Proficiency in software development (.NET, C/C++, Python, Java) Ability to design data processing pipelines, storage structures, and automation for both on-premise and cloud computing environments Experience with extraction, transformation, and loading (ETL) of large datasets for ad-hoc analysis in Excel, Matlab, or other packages Familiarity with computer vision and OCR software Passion for cooking, culinary history, or culinary science a plus We are an equal opportunity employer | E49: 3.3 | F49: Intellectual Ventures 3.3 | G49: Bellevue, WA | H49: Bellevue, WA | I49: 501 to 1000 employees | J49: 2000 | K49: Company - Private | L49: Investment Banking & Asset Management | M49: Finance | N49: Unknown / Non-Applicable | O49: -1
